[{"vacancy_name": "Back-end Python developer", "salary_min": null, "salary_max": null, "salary_currency": null, "vacancy_link": "https://novosibirsk.hh.ru/vacancy/45424106", "site": "hh.ru"}, {"vacancy_name": "Middle Python Developer", "salary_min": null, "salary_max": null, "salary_currency": null, "vacancy_link": "https://novosibirsk.hh.ru/vacancy/45926838", "site": "hh.ru"}, {"vacancy_name": "Python Developer", "salary_min": null, "salary_max": null, "salary_currency": null, "vacancy_link": "https://novosibirsk.hh.ru/vacancy/44369407", "site": "hh.ru"}, {"vacancy_name": "Senior Backend Developer (Web app, Python, FastAPI) / \u0423\u0434\u0430\u043b\u0435\u043d\u043d\u043e", "salary_min": null, "salary_max": null, "salary_currency": null, "vacancy_link": "https://novosibirsk.hh.ru/vacancy/45862360", "site": "hh.ru"}, {"vacancy_name": "Python Developer", "salary_min": null, "salary_max": null, "salary_currency": null, "vacancy_link": "https://novosibirsk.hh.ru/vacancy/45814558", "site": "hh.ru"}, {"vacancy_name": "Python-\u0440\u0430\u0437\u0440\u0430\u0431\u043e\u0442\u0447\u0438\u043a (Django, DRF)", "salary_min": null, "salary_max": null, "salary_currency": null, "vacancy_link": "https://novosibirsk.hh.ru/vacancy/39736489", "site": "hh.ru"}, {"vacancy_name": "Python developer", "salary_min": null, "salary_max": null, "salary_currency": null, "vacancy_link": "https://novosibirsk.hh.ru/vacancy/45978267", "site": "hh.ru"}, {"vacancy_name": "Python developer", "salary_min": null, "salary_max": null, "salary_currency": null, "vacancy_link": "https://novosibirsk.hh.ru/vacancy/30005963", "site": "hh.ru"}, {"vacancy_name": "Junior \u0440\u0430\u0437\u0440\u0430\u0431\u043e\u0442\u0447\u0438\u043a Python Django", "salary_min": null, "salary_max": null, "salary_currency": null, "vacancy_link": "https://novosibirsk.hh.ru/vacancy/45517979", "site": "hh.ru"}, {"vacancy_name": "\u0420\u0430\u0437\u0440\u0430\u0431\u043e\u0442\u0447\u0438\u043a Python / \u041f\u0440\u043e\u0433\u0440\u0430\u043c\u043c\u0438\u0441\u0442 Python", "salary_min": null, "salary_max": null, "salary_currency": null, "vacancy_link": "https://novosibirsk.hh.ru/vacancy/45428063", "site": "hh.ru"}, {"vacancy_name": "Junior Python developer (\u0432 \u0421\u043e\u0447\u0438)", "salary_min": null, "salary_max": null, "salary_currency": null, "vacancy_link": "https://novosibirsk.hh.ru/vacancy/45849649", "site": "hh.ru"}, {"vacancy_name": "\u041f\u0440\u043e\u0433\u0440\u0430\u043c\u043c\u0438\u0441\u0442 Python", "salary_min": null, "salary_max": null, "salary_currency": null, "vacancy_link": "https://novosibirsk.hh.ru/vacancy/45943518", "site": "hh.ru"}, {"vacancy_name": "\u0420\u0430\u0437\u0440\u0430\u0431\u043e\u0442\u0447\u0438\u043a-Python (Django, DRF)", "salary_min": null, "salary_max": null, "salary_currency": null, "vacancy_link": "https://novosibirsk.hh.ru/vacancy/43242292", "site": "hh.ru"}, {"vacancy_name": "Junior Python Developer", "salary_min": null, "salary_max": null, "salary_currency": null, "vacancy_link": "https://novosibirsk.hh.ru/vacancy/45974479", "site": "hh.ru"}, {"vacancy_name": "Python developer / Python \u0440\u0430\u0437\u0440\u0430\u0431\u043e\u0442\u0447\u0438\u043a / \u041f\u0440\u043e\u0433\u0440\u0430\u043c\u043c\u0438\u0441\u0442 Python", "salary_min": null, "salary_max": null, "salary_currency": null, "vacancy_link": "https://novosibirsk.hh.ru/vacancy/45850841", "site": "hh.ru"}, {"vacancy_name": "\u0421\u0442\u0430\u0436\u0435\u0440-\u043f\u0440\u043e\u0433\u0440\u0430\u043c\u043c\u0438\u0441\u0442 Python", "salary_min": null, "salary_max": null, "salary_currency": null, "vacancy_link": "https://novosibirsk.hh.ru/vacancy/45573740", "site": "hh.ru"}, {"vacancy_name": "Python Engineer", "salary_min": null, "salary_max": null, "salary_currency": null, "vacancy_link": "https://novosibirsk.hh.ru/vacancy/45563410", "site": "hh.ru"}, {"vacancy_name": "\u0421\u0442\u0430\u0436\u0435\u0440-\u0440\u0430\u0437\u0440\u0430\u0431\u043e\u0442\u0447\u0438\u043a Python", "salary_min": null, "salary_max": null, "salary_currency": null, "vacancy_link": "https://novosibirsk.hh.ru/vacancy/45928486", "site": "hh.ru"}, {"vacancy_name": "Python Developer", "salary_min": null, "salary_max": null, "salary_currency": null, "vacancy_link": "https://novosibirsk.hh.ru/vacancy/45833430", "site": "hh.ru"}, {"vacancy_name": "Python django-\u0440\u0430\u0437\u0440\u0430\u0431\u043e\u0442\u0447\u0438\u043a (\u043a\u0440\u0438\u043f\u0442\u043e\u0432\u0430\u043b\u044e\u0442\u043d\u044b\u0439 \u0441\u0435\u0440\u0432\u0438\u0441)", "salary_min": null, "salary_max": null, "salary_currency": null, "vacancy_link": "https://novosibirsk.hh.ru/vacancy/45761998", "site": "hh.ru"}, {"vacancy_name": "Python Developer", "salary_min": null, "salary_max": null, "salary_currency": null, "vacancy_link": "https://novosibirsk.hh.ru/vacancy/45434257", "site": "hh.ru"}, {"vacancy_name": "Python \u0440\u0430\u0437\u0440\u0430\u0431\u043e\u0442\u0447\u0438\u043a", "salary_min": null, "salary_max": null, "salary_currency": null, "vacancy_link": "https://novosibirsk.hh.ru/vacancy/45312269", "site": "hh.ru"}, {"vacancy_name": "Middle QA Automation Engineer (Python)", "salary_min": null, "salary_max": null, "salary_currency": null, "vacancy_link": "https://novosibirsk.hh.ru/vacancy/43394113", "site": "hh.ru"}, {"vacancy_name": "\u0420\u0430\u0437\u0440\u0430\u0431\u043e\u0442\u0447\u0438\u043a Python", "salary_min": null, "salary_max": null, "salary_currency": null, "vacancy_link": "https://novosibirsk.hh.ru/vacancy/45306682", "site": "hh.ru"}, {"vacancy_name": "\u0420\u0430\u0437\u0440\u0430\u0431\u043e\u0442\u0447\u0438\u043a \u0430\u0432\u0442\u043e\u043c\u0430\u0442\u0438\u0447\u0435\u0441\u043a\u0438\u0445 \u0442\u0435\u0441\u0442\u043e\u0432 GUI (Python, Squish)", "salary_min": null, "salary_max": null, "salary_currency": null, "vacancy_link": "https://novosibirsk.hh.ru/vacancy/45657026", "site": "hh.ru"}, {"vacancy_name": "Python-\u0440\u0430\u0437\u0440\u0430\u0431\u043e\u0442\u0447\u0438\u043a (Middle)", "salary_min": null, "salary_max": null, "salary_currency": null, "vacancy_link": "https://novosibirsk.hh.ru/vacancy/45662231", "site": "hh.ru"}, {"vacancy_name": "\u0412\u0435\u0434\u0443\u0449\u0438\u0439 Python \u0420\u0430\u0437\u0440\u0430\u0431\u043e\u0442\u0447\u0438\u043a", "salary_min": null, "salary_max": null, "salary_currency": null, "vacancy_link": "https://novosibirsk.hh.ru/vacancy/45818601", "site": "hh.ru"}, {"vacancy_name": "\u041c\u043b\u0430\u0434\u0448\u0438\u0439 \u0440\u0430\u0437\u0440\u0430\u0431\u043e\u0442\u0447\u0438\u043a Python, \u041c\u0430\u0440\u043a\u0435\u0442\u043f\u043b\u0435\u0439\u0441", "salary_min": null, "salary_max": null, "salary_currency": null, "vacancy_link": "https://novosibirsk.hh.ru/vacancy/45927927", "site": "hh.ru"}, {"vacancy_name": "Python Developer", "salary_min": null, "salary_max": null, "salary_currency": null, "vacancy_link": "https://novosibirsk.hh.ru/vacancy/45714635", "site": "hh.ru"}, {"vacancy_name": "Middle Python developer (\u0440\u0435\u043b\u043e\u043a\u0430\u0446\u0438\u044f \u0432 \u0421\u043e\u0447\u0438)", "salary_min": null, "salary_max": null, "salary_currency": null, "vacancy_link": "https://novosibirsk.hh.ru/vacancy/45414767", "site": "hh.ru"}, {"vacancy_name": "Senior Python Developer", "salary_min": null, "salary_max": null, "salary_currency": null, "vacancy_link": "https://novosibirsk.hh.ru/vacancy/45541962", "site": "hh.ru"}, {"vacancy_name": "Python developer", "salary_min": null, "salary_max": null, "salary_currency": null, "vacancy_link": "https://novosibirsk.hh.ru/vacancy/45961829", "site": "hh.ru"}, {"vacancy_name": "Python/Django Web Developer", "salary_min": null, "salary_max": null, "salary_currency": null, "vacancy_link": "https://novosibirsk.hh.ru/vacancy/45544768", "site": "hh.ru"}, {"vacancy_name": "\u041f\u0440\u043e\u0433\u0440\u0430\u043c\u043c\u0438\u0441\u0442 Python Backend", "salary_min": null, "salary_max": null, "salary_currency": null, "vacancy_link": "https://novosibirsk.hh.ru/vacancy/45826843", "site": "hh.ru"}, {"vacancy_name": "Python \u0440\u0430\u0437\u0440\u0430\u0431\u043e\u0442\u0447\u0438\u043a", "salary_min": null, "salary_max": null, "salary_currency": null, "vacancy_link": "https://novosibirsk.hh.ru/vacancy/45400578", "site": "hh.ru"}, {"vacancy_name": "Backend- \u0440\u0430\u0437\u0440\u0430\u0431\u043e\u0442\u0447\u0438\u043a Middle+/Senior (Python)", "salary_min": null, "salary_max": null, "salary_currency": null, "vacancy_link": "https://novosibirsk.hh.ru/vacancy/45537377", "site": "hh.ru"}, {"vacancy_name": "Python Developer", "salary_min": null, "salary_max": null, "salary_currency": null, "vacancy_link": "https://novosibirsk.hh.ru/vacancy/45950911", "site": "hh.ru"}, {"vacancy_name": "Python developer", "salary_min": null, "salary_max": null, "salary_currency": null, "vacancy_link": "https://novosibirsk.hh.ru/vacancy/45728416", "site": "hh.ru"}, {"vacancy_name": "\u0412\u0435\u0434\u0443\u0449\u0438\u0439 Python \u0420\u0430\u0437\u0440\u0430\u0431\u043e\u0442\u0447\u0438\u043a", "salary_min": null, "salary_max": null, "salary_currency": null, "vacancy_link": "https://novosibirsk.hh.ru/vacancy/45818618", "site": "hh.ru"}, {"vacancy_name": "Python developer", "salary_min": null, "salary_max": null, "salary_currency": null, "vacancy_link": "https://novosibirsk.hh.ru/vacancy/45727983", "site": "hh.ru"}, {"vacancy_name": "Software Developer Python", "salary_min": null, "salary_max": null, "salary_currency": null, "vacancy_link": "https://novosibirsk.hh.ru/vacancy/45435296", "site": "hh.ru"}, {"vacancy_name": "Python Developer", "salary_min": null, "salary_max": null, "salary_currency": null, "vacancy_link": "https://novosibirsk.hh.ru/vacancy/45988593", "site": "hh.ru"}, {"vacancy_name": "Python Team Lead (Django)", "salary_min": null, "salary_max": null, "salary_currency": null, "vacancy_link": "https://novosibirsk.hh.ru/vacancy/45673176", "site": "hh.ru"}, {"vacancy_name": "Python developer", "salary_min": null, "salary_max": null, "salary_currency": null, "vacancy_link": "https://novosibirsk.hh.ru/vacancy/44807060", "site": "hh.ru"}, {"vacancy_name": "Python \u0440\u0430\u0437\u0440\u0430\u0431\u043e\u0442\u0447\u0438\u043a", "salary_min": null, "salary_max": null, "salary_currency": null, "vacancy_link": "https://novosibirsk.hh.ru/vacancy/45914983", "site": "hh.ru"}, {"vacancy_name": "\u0420\u0430\u0437\u0440\u0430\u0431\u043e\u0442\u0447\u0438\u043a Python, \u041f\u043e\u0438\u0441\u043a / \u0421\u0442\u0435\u043d\u0434 \u043c\u0435\u0442\u0440\u0438\u043a", "salary_min": null, "salary_max": null, "salary_currency": null, "vacancy_link": "https://novosibirsk.hh.ru/vacancy/44524198", "site": "hh.ru"}, {"vacancy_name": "\u041f\u0440\u043e\u0433\u0440\u0430\u043c\u043c\u0438\u0441\u0442 Python (\u043f\u0440\u0438\u043a\u043b\u0430\u0434\u043d\u0430\u044f \u043c\u0430\u0442\u0435\u043c\u0430\u0442\u0438\u043a\u0430)", "salary_min": null, "salary_max": null, "salary_currency": null, "vacancy_link": "https://novosibirsk.hh.ru/vacancy/41781473", "site": "hh.ru"}, {"vacancy_name": "Python/Django Web Developer (Remote)", "salary_min": null, "salary_max": null, "salary_currency": null, "vacancy_link": "https://novosibirsk.hh.ru/vacancy/45544766", "site": "hh.ru"}, {"vacancy_name": "Python Tech Lead Engineer (Remote)", "salary_min": null, "salary_max": null, "salary_currency": null, "vacancy_link": "https://novosibirsk.hh.ru/vacancy/45755996", "site": "hh.ru"}, {"vacancy_name": "\u041f\u0440\u043e\u0433\u0440\u0430\u043c\u043c\u0438\u0441\u0442 Python/Django (\u0443\u0434\u0430\u043b\u0435\u043d\u043d\u043e)", "salary_min": null, "salary_max": null, "salary_currency": null, "vacancy_link": "https://novosibirsk.hh.ru/vacancy/45936789", "site": "hh.ru"}, {"vacancy_name": "Python \u0440\u0430\u0437\u0440\u0430\u0431\u043e\u0442\u0447\u0438\u043a", "salary_min": null, "salary_max": null, "salary_currency": null, "vacancy_link": "https://novosibirsk.hh.ru/vacancy/45537379", "site": "hh.ru"}, {"vacancy_name": "Python backend developer", "salary_min": null, "salary_max": null, "salary_currency": null, "vacancy_link": "https://novosibirsk.hh.ru/vacancy/45929244", "site": "hh.ru"}, {"vacancy_name": "Python-\u0440\u0430\u0437\u0440\u0430\u0431\u043e\u0442\u0447\u0438\u043a", "salary_min": null, "salary_max": null, "salary_currency": null, "vacancy_link": "https://novosibirsk.hh.ru/vacancy/45377497", "site": "hh.ru"}, {"vacancy_name": "Middle Python Backend developer", "salary_min": null, "salary_max": null, "salary_currency": null, "vacancy_link": "https://novosibirsk.hh.ru/vacancy/45541521", "site": "hh.ru"}, {"vacancy_name": "Python Developer (Customization Blitz)", "salary_min": null, "salary_max": null, "salary_currency": null, "vacancy_link": "https://novosibirsk.hh.ru/vacancy/45272744", "site": "hh.ru"}, {"vacancy_name": "Python developer (remote)", "salary_min": null, "salary_max": null, "salary_currency": null, "vacancy_link": "https://novosibirsk.hh.ru/vacancy/44228873", "site": "hh.ru"}, {"vacancy_name": "Backend- \u0440\u0430\u0437\u0440\u0430\u0431\u043e\u0442\u0447\u0438\u043a Middle+/Senior (Python)", "salary_min": null, "salary_max": null, "salary_currency": null, "vacancy_link": "https://novosibirsk.hh.ru/vacancy/45369089", "site": "hh.ru"}, {"vacancy_name": "Python Developer", "salary_min": null, "salary_max": null, "salary_currency": null, "vacancy_link": "https://novosibirsk.hh.ru/vacancy/44919350", "site": "hh.ru"}, {"vacancy_name": "Python-\u0440\u0430\u0437\u0440\u0430\u0431\u043e\u0442\u0447\u0438\u043a", "salary_min": null, "salary_max": null, "salary_currency": null, "vacancy_link": "https://novosibirsk.hh.ru/vacancy/45956715", "site": "hh.ru"}, {"vacancy_name": "Team Lead (Python)", "salary_min": null, "salary_max": null, "salary_currency": null, "vacancy_link": "https://novosibirsk.hh.ru/vacancy/45669461", "site": "hh.ru"}, {"vacancy_name": "Python Developer", "salary_min": null, "salary_max": null, "salary_currency": null, "vacancy_link": "https://novosibirsk.hh.ru/vacancy/45682539", "site": "hh.ru"}, {"vacancy_name": "Data engineer (Python)", "salary_min": null, "salary_max": null, "salary_currency": null, "vacancy_link": "https://novosibirsk.hh.ru/vacancy/43102927", "site": "hh.ru"}, {"vacancy_name": "Python developer", "salary_min": null, "salary_max": null, "salary_currency": null, "vacancy_link": "https://novosibirsk.hh.ru/vacancy/44783317", "site": "hh.ru"}, {"vacancy_name": "Senior Python Developer (\u0443\u0434\u0430\u043b\u0435\u043d\u043d\u043e)", "salary_min": null, "salary_max": null, "salary_currency": null, "vacancy_link": "https://novosibirsk.hh.ru/vacancy/45468885", "site": "hh.ru"}, {"vacancy_name": "Python Middle Developer", "salary_min": null, "salary_max": null, "salary_currency": null, "vacancy_link": "https://novosibirsk.hh.ru/vacancy/44401060", "site": "hh.ru"}, {"vacancy_name": "Python Developer ( junior+ / middle, team lead )", "salary_min": null, "salary_max": null, "salary_currency": null, "vacancy_link": "https://novosibirsk.hh.ru/vacancy/45125964", "site": "hh.ru"}, {"vacancy_name": "Python backend developer", "salary_min": null, "salary_max": null, "salary_currency": null, "vacancy_link": "https://novosibirsk.hh.ru/vacancy/45929244", "site": "hh.ru"}, {"vacancy_name": "Python-\u0440\u0430\u0437\u0440\u0430\u0431\u043e\u0442\u0447\u0438\u043a \u0432 \u041f\u0440\u043e\u0446\u0435\u0441\u0441\u044b \u0431\u044d\u043a-\u043e\u0444\u0438\u0441\u0430", "salary_min": null, "salary_max": null, "salary_currency": null, "vacancy_link": "https://novosibirsk.hh.ru/vacancy/45984455", "site": "hh.ru"}, {"vacancy_name": "Python \u0440\u0430\u0437\u0440\u0430\u0431\u043e\u0442\u0447\u0438\u043a (Team lead / senior / middle ) (\u0443\u0434\u0430\u043b\u0435\u043d\u043d\u043e)", "salary_min": null, "salary_max": null, "salary_currency": null, "vacancy_link": "https://novosibirsk.hh.ru/vacancy/45816936", "site": "hh.ru"}, {"vacancy_name": "Python Teamlead/Senior Python Developer", "salary_min": null, "salary_max": null, "salary_currency": null, "vacancy_link": "https://novosibirsk.hh.ru/vacancy/45786414", "site": "hh.ru"}, {"vacancy_name": "\u041f\u0440\u043e\u0433\u0440\u0430\u043c\u043c\u0438\u0441\u0442 Python", "salary_min": null, "salary_max": null, "salary_currency": null, "vacancy_link": "https://novosibirsk.hh.ru/vacancy/43998374", "site": "hh.ru"}, {"vacancy_name": "Full-stack Developer (React, Python)", "salary_min": null, "salary_max": null, "salary_currency": null, "vacancy_link": "https://novosibirsk.hh.ru/vacancy/45382279", "site": "hh.ru"}, {"vacancy_name": "\u0420\u0430\u0437\u0440\u0430\u0431\u043e\u0442\u0447\u0438\u043a Python (Automoderation)", "salary_min": null, "salary_max": null, "salary_currency": null, "vacancy_link": "https://novosibirsk.hh.ru/vacancy/45768579", "site": "hh.ru"}, {"vacancy_name": "\u041f\u0440\u043e\u0433\u0440\u0430\u043c\u043c\u0438\u0441\u0442 Python", "salary_min": null, "salary_max": null, "salary_currency": null, "vacancy_link": "https://novosibirsk.hh.ru/vacancy/40030321", "site": "hh.ru"}, {"vacancy_name": "Middle \u0440\u0430\u0437\u0440\u0430\u0431\u043e\u0442\u0447\u0438\u043a Python", "salary_min": null, "salary_max": null, "salary_currency": null, "vacancy_link": "https://novosibirsk.hh.ru/vacancy/45955867", "site": "hh.ru"}, {"vacancy_name": "Python-teamlead", "salary_min": null, "salary_max": null, "salary_currency": null, "vacancy_link": "https://novosibirsk.hh.ru/vacancy/45113218", "site": "hh.ru"}, {"vacancy_name": "Middle / Senior Python developer", "salary_min": null, "salary_max": null, "salary_currency": null, "vacancy_link": "https://novosibirsk.hh.ru/vacancy/45750224", "site": "hh.ru"}, {"vacancy_name": "Python\\Django \u0440\u0430\u0437\u0440\u0430\u0431\u043e\u0442\u0447\u0438\u043a (Middle / Senior)", "salary_min": null, "salary_max": null, "salary_currency": null, "vacancy_link": "https://novosibirsk.hh.ru/vacancy/43661942", "site": "hh.ru"}, {"vacancy_name": "Python developer", "salary_min": null, "salary_max": null, "salary_currency": null, "vacancy_link": "https://novosibirsk.hh.ru/vacancy/45790381", "site": "hh.ru"}, {"vacancy_name": "Python Fullstack \u0420\u0430\u0437\u0440\u0430\u0431\u043e\u0442\u0447\u0438\u043a", "salary_min": null, "salary_max": null, "salary_currency": null, "vacancy_link": "https://novosibirsk.hh.ru/vacancy/44681248", "site": "hh.ru"}, {"vacancy_name": "Python Senior", "salary_min": null, "salary_max": null, "salary_currency": null, "vacancy_link": "https://novosibirsk.hh.ru/vacancy/45613917", "site": "hh.ru"}, {"vacancy_name": "Middle Python developer", "salary_min": null, "salary_max": null, "salary_currency": null, "vacancy_link": "https://novosibirsk.hh.ru/vacancy/45930395", "site": "hh.ru"}, {"vacancy_name": "Senior Python Engineer (Big Data) for Data Platform Team", "salary_min": null, "salary_max": null, "salary_currency": null, "vacancy_link": "https://novosibirsk.hh.ru/vacancy/45987344", "site": "hh.ru"}, {"vacancy_name": "Back-End \u0440\u0430\u0437\u0440\u0430\u0431\u043e\u0442\u0447\u0438\u043a - Python", "salary_min": null, "salary_max": null, "salary_currency": null, "vacancy_link": "https://novosibirsk.hh.ru/vacancy/45598333", "site": "hh.ru"}, {"vacancy_name": "Python Backend Developer (\u0421\u0431\u0435\u0440\u0417\u0432\u0443\u043a \u0434\u043b\u044f \u0431\u0438\u0437\u043d\u0435\u0441\u0430)", "salary_min": null, "salary_max": null, "salary_currency": null, "vacancy_link": "https://novosibirsk.hh.ru/vacancy/45306109", "site": "hh.ru"}, {"vacancy_name": "Senior Python Developer", "salary_min": null, "salary_max": null, "salary_currency": null, "vacancy_link": "https://novosibirsk.hh.ru/vacancy/44220581", "site": "hh.ru"}, {"vacancy_name": "\u041f\u0440\u043e\u0433\u0440\u0430\u043c\u043c\u0438\u0441\u0442 C/C++/Python, \u0441\u0435\u0442\u0435\u0432\u043e\u0439 \u0441\u0442\u0435\u043a OPENWRT/Linux (\u0447\u0430\u0441\u0442\u0438\u0447\u043d\u0430\u044f \u0437\u0430\u043d\u044f\u0442\u043e\u0441\u0442\u044c)", "salary_min": null, "salary_max": null, "salary_currency": null, "vacancy_link": "https://novosibirsk.hh.ru/vacancy/45672749", "site": "hh.ru"}, {"vacancy_name": "Python Developer", "salary_min": null, "salary_max": null, "salary_currency": null, "vacancy_link": "https://novosibirsk.hh.ru/vacancy/42141155", "site": "hh.ru"}, {"vacancy_name": "Python \u0440\u0430\u0437\u0440\u0430\u0431\u043e\u0442\u0447\u0438\u043a", "salary_min": null, "salary_max": null, "salary_currency": null, "vacancy_link": "https://novosibirsk.hh.ru/vacancy/44882559", "site": "hh.ru"}, {"vacancy_name": "Python Developer / Python \u0440\u0430\u0437\u0440\u0430\u0431\u043e\u0442\u0447\u0438\u043a", "salary_min": null, "salary_max": null, "salary_currency": null, "vacancy_link": "https://novosibirsk.hh.ru/vacancy/45910979", "site": "hh.ru"}, {"vacancy_name": "Java/Python/Scala-\u0440\u0430\u0437\u0440\u0430\u0431\u043e\u0442\u0447\u0438\u043a \u0432 Big Data", "salary_min": null, "salary_max": null, "salary_currency": null, "vacancy_link": "https://novosibirsk.hh.ru/vacancy/44352347", "site": "hh.ru"}, {"vacancy_name": "Python Developer Middle/Senior (\u0423\u0434\u0430\u043b\u0435\u043d\u043d\u043e)", "salary_min": null, "salary_max": null, "salary_currency": null, "vacancy_link": "https://novosibirsk.hh.ru/vacancy/41727993", "site": "hh.ru"}, {"vacancy_name": "Senior Python Developer", "salary_min": null, "salary_max": null, "salary_currency": null, "vacancy_link": "https://novosibirsk.hh.ru/vacancy/44878097", "site": "hh.ru"}, {"vacancy_name": "\u0420\u0430\u0437\u0440\u0430\u0431\u043e\u0442\u0447\u0438\u043a C++/Python(ML, \u0441\u0438\u0441\u0442\u0435\u043c\u044b \u043a\u043e\u043c\u043f\u044c\u044e\u0442\u0435\u0440\u043d\u043e\u0433\u043e \u0437\u0440\u0435\u043d\u0438\u044f)", "salary_min": null, "salary_max": null, "salary_currency": null, "vacancy_link": "https://novosibirsk.hh.ru/vacancy/45937617", "site": "hh.ru"}, {"vacancy_name": "Back-end \u0440\u0430\u0437\u0440\u0430\u0431\u043e\u0442\u0447\u0438\u043a (Python)", "salary_min": null, "salary_max": null, "salary_currency": null, "vacancy_link": "https://novosibirsk.hh.ru/vacancy/45918465", "site": "hh.ru"}, {"vacancy_name": "Python-\u0440\u0430\u0437\u0440\u0430\u0431\u043e\u0442\u0447\u0438\u043a \u0432 \u042f\u043d\u0434\u0435\u043a\u0441.\u041f\u0440\u0430\u043a\u0442\u0438\u043a\u0443\u043c", "salary_min": null, "salary_max": null, "salary_currency": null, "vacancy_link": "https://novosibirsk.hh.ru/vacancy/45985257", "site": "hh.ru"}, {"vacancy_name": "\u041f\u0440\u043e\u0433\u0440\u0430\u043c\u043c\u0438\u0441\u0442 Python", "salary_min": null, "salary_max": null, "salary_currency": null, "vacancy_link": "https://novosibirsk.hh.ru/vacancy/44570552", "site": "hh.ru"}, {"vacancy_name": "Python test Automation Engineer (Cloud Systems)", "salary_min": null, "salary_max": null, "salary_currency": null, "vacancy_link": "https://novosibirsk.hh.ru/vacancy/43430071", "site": "hh.ru"}, {"vacancy_name": "Python Developer", "salary_min": null, "salary_max": null, "salary_currency": null, "vacancy_link": "https://novosibirsk.hh.ru/vacancy/45876623", "site": "hh.ru"}, {"vacancy_name": "\u0420\u0430\u0437\u0440\u0430\u0431\u043e\u0442\u0447\u0438\u043a Python", "salary_min": null, "salary_max": null, "salary_currency": null, "vacancy_link": "https://novosibirsk.hh.ru/vacancy/45842468", "site": "hh.ru"}, {"vacancy_name": "Python/ Scala \u0440\u0430\u0437\u0440\u0430\u0431\u043e\u0442\u0447\u0438\u043a", "salary_min": null, "salary_max": null, "salary_currency": null, "vacancy_link": "https://novosibirsk.hh.ru/vacancy/45873988", "site": "hh.ru"}, {"vacancy_name": "Python developer", "salary_min": null, "salary_max": null, "salary_currency": null, "vacancy_link": "https://novosibirsk.hh.ru/vacancy/44261477", "site": "hh.ru"}, {"vacancy_name": "Python-\u0440\u0430\u0437\u0440\u0430\u0431\u043e\u0442\u0447\u0438\u043a", "salary_min": null, "salary_max": null, "salary_currency": null, "vacancy_link": "https://novosibirsk.hh.ru/vacancy/45309802", "site": "hh.ru"}, {"vacancy_name": "Python developer", "salary_min": null, "salary_max": null, "salary_currency": null, "vacancy_link": "https://novosibirsk.hh.ru/vacancy/37583293", "site": "hh.ru"}, {"vacancy_name": "Python Team Lead", "salary_min": null, "salary_max": null, "salary_currency": null, "vacancy_link": "https://novosibirsk.hh.ru/vacancy/45843801", "site": "hh.ru"}, {"vacancy_name": "\u041f\u0440\u043e\u0433\u0440\u0430\u043c\u043c\u0438\u0441\u0442 Python", "salary_min": null, "salary_max": null, "salary_currency": null, "vacancy_link": "https://novosibirsk.hh.ru/vacancy/44570552", "site": "hh.ru"}, {"vacancy_name": "\u041f\u0440\u043e\u0433\u0440\u0430\u043c\u043c\u0438\u0441\u0442 Python", "salary_min": null, "salary_max": null, "salary_currency": null, "vacancy_link": "https://novosibirsk.hh.ru/vacancy/45851387", "site": "hh.ru"}, {"vacancy_name": "Python Team Lead", "salary_min": null, "salary_max": null, "salary_currency": null, "vacancy_link": "https://novosibirsk.hh.ru/vacancy/45843922", "site": "hh.ru"}, {"vacancy_name": "Python Developer", "salary_min": null, "salary_max": null, "salary_currency": null, "vacancy_link": "https://novosibirsk.hh.ru/vacancy/45867089", "site": "hh.ru"}, {"vacancy_name": "Python backend \u0440\u0430\u0437\u0440\u0430\u0431\u043e\u0442\u0447\u0438\u043a", "salary_min": null, "salary_max": null, "salary_currency": null, "vacancy_link": "https://novosibirsk.hh.ru/vacancy/45813276", "site": "hh.ru"}, {"vacancy_name": "Junior python \u0440\u0430\u0437\u0440\u0430\u0431\u043e\u0442\u0447\u0438\u043a (\u0440\u0430\u0437\u0440\u0430\u0431\u043e\u0442\u0447\u0438\u043a \u043b\u043e\u0433\u0438\u043a\u0438)", "salary_min": null, "salary_max": null, "salary_currency": null, "vacancy_link": "https://novosibirsk.hh.ru/vacancy/45799941", "site": "hh.ru"}, {"vacancy_name": "\u041f\u0440\u043e\u0433\u0440\u0430\u043c\u043c\u0438\u0441\u0442 Python", "salary_min": null, "salary_max": null, "salary_currency": null, "vacancy_link": "https://novosibirsk.hh.ru/vacancy/45461037", "site": "hh.ru"}, {"vacancy_name": "Senior Python Engineer", "salary_min": null, "salary_max": null, "salary_currency": null, "vacancy_link": "https://novosibirsk.hh.ru/vacancy/44480720", "site": "hh.ru"}, {"vacancy_name": "\u041f\u0440\u043e\u0433\u0440\u0430\u043c\u043c\u0438\u0441\u0442 Python", "salary_min": null, "salary_max": null, "salary_currency": null, "vacancy_link": "https://novosibirsk.hh.ru/vacancy/43156201", "site": "hh.ru"}, {"vacancy_name": "QA-\u0438\u043d\u0436\u0435\u043d\u0435\u0440 (automation, python) \u0432 \u043a\u043e\u043c\u0430\u043d\u0434\u0443 Online", "salary_min": null, "salary_max": null, "salary_currency": null, "vacancy_link": "https://novosibirsk.hh.ru/vacancy/45245929", "site": "hh.ru"}, {"vacancy_name": "\u0418\u043d\u0436\u0435\u043d\u0435\u0440-\u043f\u0440\u043e\u0433\u0440\u0430\u043c\u043c\u0438\u0441\u0442 Python", "salary_min": null, "salary_max": null, "salary_currency": null, "vacancy_link": "https://novosibirsk.hh.ru/vacancy/45548066", "site": "hh.ru"}, {"vacancy_name": "Python - \u0440\u0430\u0437\u0440\u0430\u0431\u043e\u0442\u0447\u0438\u043a (Middle)", "salary_min": null, "salary_max": null, "salary_currency": null, "vacancy_link": "https://novosibirsk.hh.ru/vacancy/42523312", "site": "hh.ru"}, {"vacancy_name": "Senior/Middle backend-\u0440\u0430\u0437\u0440\u0430\u0431\u043e\u0442\u0447\u0438\u043a (Python, Django)", "salary_min": null, "salary_max": null, "salary_currency": null, "vacancy_link": "https://novosibirsk.hh.ru/vacancy/43298031", "site": "hh.ru"}, {"vacancy_name": "\u0420\u0430\u0437\u0440\u0430\u0431\u043e\u0442\u0447\u0438\u043a Python", "salary_min": null, "salary_max": null, "salary_currency": null, "vacancy_link": "https://novosibirsk.hh.ru/vacancy/45143092", "site": "hh.ru"}, {"vacancy_name": "Senior Python Developer", "salary_min": null, "salary_max": null, "salary_currency": null, "vacancy_link": "https://novosibirsk.hh.ru/vacancy/45050219", "site": "hh.ru"}, {"vacancy_name": "Python middle developer/ Python-\u0420\u0430\u0437\u0440\u0430\u0431\u043e\u0442\u0447\u0438\u043a", "salary_min": null, "salary_max": null, "salary_currency": null, "vacancy_link": "https://novosibirsk.hh.ru/vacancy/45785483", "site": "hh.ru"}, {"vacancy_name": "\u0412\u0435\u0434\u0443\u0449\u0438\u0439 Python \u0440\u0430\u0437\u0440\u0430\u0431\u043e\u0442\u0447\u0438\u043a", "salary_min": null, "salary_max": null, "salary_currency": null, "vacancy_link": "https://novosibirsk.hh.ru/vacancy/45843651", "site": "hh.ru"}, {"vacancy_name": "Python \u0440\u0430\u0437\u0440\u0430\u0431\u043e\u0442\u0447\u0438\u043a Senior", "salary_min": null, "salary_max": null, "salary_currency": null, "vacancy_link": "https://novosibirsk.hh.ru/vacancy/41541061", "site": "hh.ru"}, {"vacancy_name": "Python Team Lead", "salary_min": null, "salary_max": null, "salary_currency": null, "vacancy_link": "https://novosibirsk.hh.ru/vacancy/45843785", "site": "hh.ru"}, {"vacancy_name": "Senior Python Developer", "salary_min": null, "salary_max": null, "salary_currency": null, "vacancy_link": "https://novosibirsk.hh.ru/vacancy/45689184", "site": "hh.ru"}, {"vacancy_name": "Middle/Senior Python \u0440\u0430\u0437\u0440\u0430\u0431\u043e\u0442\u0447\u0438\u043a", "salary_min": null, "salary_max": null, "salary_currency": null, "vacancy_link": "https://novosibirsk.hh.ru/vacancy/44779981", "site": "hh.ru"}, {"vacancy_name": "Python Developer (Technical Support)", "salary_min": null, "salary_max": null, "salary_currency": null, "vacancy_link": "https://novosibirsk.hh.ru/vacancy/44367322", "site": "hh.ru"}, {"vacancy_name": "Senior Python Developer (MTS AI)", "salary_min": null, "salary_max": null, "salary_currency": null, "vacancy_link": "https://novosibirsk.hh.ru/vacancy/45297306", "site": "hh.ru"}, {"vacancy_name": "Middle / Senior Python developer", "salary_min": null, "salary_max": null, "salary_currency": null, "vacancy_link": "https://novosibirsk.hh.ru/vacancy/30548119", "site": "hh.ru"}, {"vacancy_name": "Python \u0440\u0430\u0437\u0440\u0430\u0431\u043e\u0442\u0447\u0438\u043a", "salary_min": null, "salary_max": null, "salary_currency": null, "vacancy_link": "https://novosibirsk.hh.ru/vacancy/42600063", "site": "hh.ru"}, {"vacancy_name": "Python \u0440\u0430\u0437\u0440\u0430\u0431\u043e\u0442\u0447\u0438\u043a (Middle+/Senior)", "salary_min": null, "salary_max": null, "salary_currency": null, "vacancy_link": "https://novosibirsk.hh.ru/vacancy/45806688", "site": "hh.ru"}, {"vacancy_name": "Senior Python Engineer / MLOps", "salary_min": null, "salary_max": null, "salary_currency": null, "vacancy_link": "https://novosibirsk.hh.ru/vacancy/45811421", "site": "hh.ru"}, {"vacancy_name": "Python \u0440\u0430\u0437\u0440\u0430\u0431\u043e\u0442\u0447\u0438\u043a", "salary_min": null, "salary_max": null, "salary_currency": null, "vacancy_link": "https://novosibirsk.hh.ru/vacancy/41179197", "site": "hh.ru"}, {"vacancy_name": "Python-\u0440\u0430\u0437\u0440\u0430\u0431\u043e\u0442\u0447\u0438\u043a (Computer vision)", "salary_min": null, "salary_max": null, "salary_currency": null, "vacancy_link": "https://novosibirsk.hh.ru/vacancy/44266270", "site": "hh.ru"}, {"vacancy_name": "Python \u0440\u0430\u0437\u0440\u0430\u0431\u043e\u0442\u0447\u0438\u043a (Middle+)", "salary_min": null, "salary_max": null, "salary_currency": null, "vacancy_link": "https://novosibirsk.hh.ru/vacancy/44863184", "site": "hh.ru"}, {"vacancy_name": "Senior/Middle Back-End Developer Python", "salary_min": null, "salary_max": null, "salary_currency": null, "vacancy_link": "https://novosibirsk.hh.ru/vacancy/45848505", "site": "hh.ru"}, {"vacancy_name": "\u0421\u0442\u0430\u0440\u0448\u0438\u0439 \u0440\u0430\u0437\u0440\u0430\u0431\u043e\u0442\u0447\u0438\u043a Python", "salary_min": null, "salary_max": null, "salary_currency": null, "vacancy_link": "https://novosibirsk.hh.ru/vacancy/44919240", "site": "hh.ru"}, {"vacancy_name": "Python Developer (remotely)", "salary_min": null, "salary_max": null, "salary_currency": null, "vacancy_link": "https://novosibirsk.hh.ru/vacancy/45786574", "site": "hh.ru"}, {"vacancy_name": "Python backend \u0440\u0430\u0437\u0440\u0430\u0431\u043e\u0442\u0447\u0438\u043a", "salary_min": null, "salary_max": null, "salary_currency": null, "vacancy_link": "https://novosibirsk.hh.ru/vacancy/45010269", "site": "hh.ru"}, {"vacancy_name": "Middle Developer (Python) \u2013 \u0440\u0430\u0437\u0440\u0430\u0431\u043e\u0442\u0447\u0438\u043a", "salary_min": null, "salary_max": null, "salary_currency": null, "vacancy_link": "https://novosibirsk.hh.ru/vacancy/44616071", "site": "hh.ru"}, {"vacancy_name": "Python \u0440\u0430\u0437\u0440\u0430\u0431\u043e\u0442\u0447\u0438\u043a \u0432 SberDevices (b2e)", "salary_min": null, "salary_max": null, "salary_currency": null, "vacancy_link": "https://novosibirsk.hh.ru/vacancy/44536394", "site": "hh.ru"}, {"vacancy_name": "Backend-\u0440\u0430\u0437\u0440\u0430\u0431\u043e\u0442\u0447\u0438\u043a Python (Django)", "salary_min": null, "salary_max": null, "salary_currency": null, "vacancy_link": "https://novosibirsk.hh.ru/vacancy/45771068", "site": "hh.ru"}, {"vacancy_name": "Senior Python-\u0440\u0430\u0437\u0440\u0430\u0431\u043e\u0442\u0447\u0438\u043a", "salary_min": null, "salary_max": null, "salary_currency": null, "vacancy_link": "https://novosibirsk.hh.ru/vacancy/45170133", "site": "hh.ru"}, {"vacancy_name": "QA Automation Engineer with Python", "salary_min": null, "salary_max": null, "salary_currency": null, "vacancy_link": "https://novosibirsk.hh.ru/vacancy/42427477", "site": "hh.ru"}, {"vacancy_name": "\u041f\u0440\u043e\u0433\u0440\u0430\u043c\u043c\u0438\u0441\u0442 Python", "salary_min": null, "salary_max": null, "salary_currency": null, "vacancy_link": "https://novosibirsk.hh.ru/vacancy/45777723", "site": "hh.ru"}, {"vacancy_name": "\u0420\u0430\u0437\u0440\u0430\u0431\u043e\u0442\u0447\u0438\u043a Python", "salary_min": null, "salary_max": null, "salary_currency": null, "vacancy_link": "https://novosibirsk.hh.ru/vacancy/43379499", "site": "hh.ru"}, {"vacancy_name": "Python fullstack \u0440\u0430\u0437\u0440\u0430\u0431\u043e\u0442\u0447\u0438\u043a, \u0443\u0434\u0430\u043b\u0435\u043d\u043d\u043e", "salary_min": null, "salary_max": null, "salary_currency": null, "vacancy_link": "https://novosibirsk.hh.ru/vacancy/45762469", "site": "hh.ru"}, {"vacancy_name": "\u0412\u0435\u0434\u0443\u0449\u0438\u0439 \u0420\u0430\u0437\u0440\u0430\u0431\u043e\u0442\u0447\u0438\u043a Python \u043e\u0444\u043b\u0430\u0439\u043d \u0438\u043d\u0442\u0435\u0433\u0440\u0430\u0446\u0438\u0438", "salary_min": null, "salary_max": null, "salary_currency": null, "vacancy_link": "https://novosibirsk.hh.ru/vacancy/44208438", "site": "hh.ru"}, {"vacancy_name": "QA automation (Python)", "salary_min": null, "salary_max": null, "salary_currency": null, "vacancy_link": "https://novosibirsk.hh.ru/vacancy/44139002", "site": "hh.ru"}, {"vacancy_name": "Data Scientist/Python Developer (remote)", "salary_min": null, "salary_max": null, "salary_currency": null, "vacancy_link": "https://novosibirsk.hh.ru/vacancy/44958328", "site": "hh.ru"}, {"vacancy_name": "Middle Backend Python/Django \u0440\u0430\u0437\u0440\u0430\u0431\u043e\u0442\u0447\u0438\u043a (\u0443\u0434\u0430\u043b\u0451\u043d\u043d\u043e)", "salary_min": null, "salary_max": null, "salary_currency": null, "vacancy_link": "https://novosibirsk.hh.ru/vacancy/45128327", "site": "hh.ru"}, {"vacancy_name": "Python Developer (SPB/Remote)", "salary_min": null, "salary_max": null, "salary_currency": null, "vacancy_link": "https://novosibirsk.hh.ru/vacancy/43536761", "site": "hh.ru"}, {"vacancy_name": "Middle Python-\u0440\u0430\u0437\u0440\u0430\u0431\u043e\u0442\u0447\u0438\u043a \u0432 \u043a\u043e\u043c\u0430\u043d\u0434\u0443 Navi", "salary_min": null, "salary_max": null, "salary_currency": null, "vacancy_link": "https://novosibirsk.hh.ru/vacancy/44385711", "site": "hh.ru"}, {"vacancy_name": "Automation QA (Python)", "salary_min": null, "salary_max": null, "salary_currency": null, "vacancy_link": "https://novosibirsk.hh.ru/vacancy/29323728", "site": "hh.ru"}, {"vacancy_name": "Senior Python Developer", "salary_min": null, "salary_max": null, "salary_currency": null, "vacancy_link": "https://novosibirsk.hh.ru/vacancy/44391852", "site": "hh.ru"}, {"vacancy_name": "Senior Python Developer for Imunify [Remote]", "salary_min": null, "salary_max": null, "salary_currency": null, "vacancy_link": "https://novosibirsk.hh.ru/vacancy/44259132", "site": "hh.ru"}, {"vacancy_name": "Python Auto Tester (Remote)", "salary_min": null, "salary_max": null, "salary_currency": null, "vacancy_link": "https://novosibirsk.hh.ru/vacancy/45799241", "site": "hh.ru"}, {"vacancy_name": "\u0412\u0435\u0434\u0443\u0449\u0438\u0439 \u043f\u0440\u043e\u0433\u0440\u0430\u043c\u043c\u0438\u0441\u0442 Python", "salary_min": null, "salary_max": null, "salary_currency": null, "vacancy_link": "https://novosibirsk.hh.ru/vacancy/36618179", "site": "hh.ru"}, {"vacancy_name": "\u0412\u0435\u0434\u0443\u0449\u0438\u0439 Python \u0440\u0430\u0437\u0440\u0430\u0431\u043e\u0442\u0447\u0438\u043a (\u0443\u0434\u0430\u043b\u0435\u043d\u043d\u043e)", "salary_min": null, "salary_max": null, "salary_currency": null, "vacancy_link": "https://novosibirsk.hh.ru/vacancy/45732842", "site": "hh.ru"}, {"vacancy_name": "\u0411\u044d\u043a\u0435\u043d\u0434-\u0440\u0430\u0437\u0440\u0430\u0431\u043e\u0442\u0447\u0438\u043a (Python)/Middle Python/ Python Developer (Remote)", "salary_min": null, "salary_max": null, "salary_currency": null, "vacancy_link": "https://novosibirsk.hh.ru/vacancy/45742803", "site": "hh.ru"}, {"vacancy_name": "Python-\u0440\u0430\u0437\u0440\u0430\u0431\u043e\u0442\u0447\u0438\u043a", "salary_min": null, "salary_max": null, "salary_currency": null, "vacancy_link": "https://novosibirsk.hh.ru/vacancy/40404075", "site": "hh.ru"}, {"vacancy_name": "Python \u0440\u0430\u0437\u0440\u0430\u0431\u043e\u0442\u0447\u0438\u043a (DevOps, DWH)", "salary_min": null, "salary_max": null, "salary_currency": null, "vacancy_link": "https://novosibirsk.hh.ru/vacancy/45862227", "site": "hh.ru"}, {"vacancy_name": "\u041f\u0440\u043e\u0433\u0440\u0430\u043c\u043c\u0438\u0441\u0442 Python", "salary_min": null, "salary_max": null, "salary_currency": null, "vacancy_link": "https://novosibirsk.hh.ru/vacancy/45738345", "site": "hh.ru"}, {"vacancy_name": "Python developer", "salary_min": null, "salary_max": null, "salary_currency": null, "vacancy_link": "https://novosibirsk.hh.ru/vacancy/44039262", "site": "hh.ru"}, {"vacancy_name": "Python engineer / developer (\u043f\u0440\u043e\u0433\u0440\u0430\u043c\u043c\u0438\u0441\u0442)", "salary_min": null, "salary_max": null, "salary_currency": null, "vacancy_link": "https://novosibirsk.hh.ru/vacancy/45745227", "site": "hh.ru"}, {"vacancy_name": "Python test Automation Engineer (Cloud Systems)", "salary_min": null, "salary_max": null, "salary_currency": null, "vacancy_link": "https://novosibirsk.hh.ru/vacancy/43430071", "site": "hh.ru"}, {"vacancy_name": "Python developer", "salary_min": null, "salary_max": null, "salary_currency": null, "vacancy_link": "https://novosibirsk.hh.ru/vacancy/45690912", "site": "hh.ru"}, {"vacancy_name": "Python developer (Middle / Senior)", "salary_min": null, "salary_max": null, "salary_currency": null, "vacancy_link": "https://novosibirsk.hh.ru/vacancy/44828907", "site": "hh.ru"}, {"vacancy_name": "\u0418\u043d\u0436\u0435\u043d\u0435\u0440-\u043f\u0440\u043e\u0433\u0440\u0430\u043c\u043c\u0438\u0441\u0442 Python", "salary_min": null, "salary_max": null, "salary_currency": null, "vacancy_link": "https://novosibirsk.hh.ru/vacancy/45398261", "site": "hh.ru"}, {"vacancy_name": "Python Developer", "salary_min": null, "salary_max": null, "salary_currency": null, "vacancy_link": "https://novosibirsk.hh.ru/vacancy/41794422", "site": "hh.ru"}, {"vacancy_name": "Senior Python Dev", "salary_min": null, "salary_max": null, "salary_currency": null, "vacancy_link": "https://novosibirsk.hh.ru/vacancy/43600813", "site": "hh.ru"}, {"vacancy_name": "\u0420\u0430\u0437\u0440\u0430\u0431\u043e\u0442\u0447\u0438\u043a Python", "salary_min": null, "salary_max": null, "salary_currency": null, "vacancy_link": "https://novosibirsk.hh.ru/vacancy/45706247", "site": "hh.ru"}, {"vacancy_name": "\u0411\u044d\u043a\u0435\u043d\u0434-\u0440\u0430\u0437\u0440\u0430\u0431\u043e\u0442\u0447\u0438\u043a (Python)/ Middle Python/ Python Developer (Remote)", "salary_min": null, "salary_max": null, "salary_currency": null, "vacancy_link": "https://novosibirsk.hh.ru/vacancy/45684271", "site": "hh.ru"}, {"vacancy_name": "Senior Python \u0440\u0430\u0437\u0440\u0430\u0431\u043e\u0442\u0447\u0438\u043a \u0432 SberDevices (\u043a\u043e\u043c\u0430\u043d\u0434\u0430 SmartMarket)", "salary_min": null, "salary_max": null, "salary_currency": null, "vacancy_link": "https://novosibirsk.hh.ru/vacancy/42667366", "site": "hh.ru"}, {"vacancy_name": "\u041f\u0440\u043e\u0433\u0440\u0430\u043c\u043c\u0438\u0441\u0442 Python (\u0443\u0434\u0430\u043b\u0435\u043d\u043d\u043e)", "salary_min": null, "salary_max": null, "salary_currency": null, "vacancy_link": "https://novosibirsk.hh.ru/vacancy/44954034", "site": "hh.ru"}, {"vacancy_name": "Full-Stack Python \u0420\u0430\u0437\u0440\u0430\u0431\u043e\u0442\u0447\u0438\u043a (Django)", "salary_min": null, "salary_max": null, "salary_currency": null, "vacancy_link": "https://novosibirsk.hh.ru/vacancy/44738683", "site": "hh.ru"}, {"vacancy_name": "\u041f\u0440\u043e\u0433\u0440\u0430\u043c\u043c\u0438\u0441\u0442 Python", "salary_min": null, "salary_max": null, "salary_currency": null, "vacancy_link": "https://novosibirsk.hh.ru/vacancy/42007512", "site": "hh.ru"}, {"vacancy_name": "\u0418\u043d\u0436\u0435\u043d\u0435\u0440-\u043f\u0440\u043e\u0433\u0440\u0430\u043c\u043c\u0438\u0441\u0442 Python", "salary_min": null, "salary_max": null, "salary_currency": null, "vacancy_link": "https://novosibirsk.hh.ru/vacancy/45398260", "site": "hh.ru"}, {"vacancy_name": "\u0420\u0430\u0437\u0440\u0430\u0431\u043e\u0442\u0447\u0438\u043a Python, \u041f\u043e\u0438\u0441\u043a / ML-\u043f\u043b\u0430\u0442\u0444\u043e\u0440\u043c\u0430", "salary_min": null, "salary_max": null, "salary_currency": null, "vacancy_link": "https://novosibirsk.hh.ru/vacancy/45716117", "site": "hh.ru"}, {"vacancy_name": "Python-\u0440\u0430\u0437\u0440\u0430\u0431\u043e\u0442\u0447\u0438\u043a \u0432 \u043a\u043e\u043c\u0430\u043d\u0434\u0443 \u0431\u0438\u043b\u043b\u0438\u043d\u0433\u0430", "salary_min": null, "salary_max": null, "salary_currency": null, "vacancy_link": "https://novosibirsk.hh.ru/vacancy/45740177", "site": "hh.ru"}, {"vacancy_name": "Backend-\u0440\u0430\u0437\u0440\u0430\u0431\u043e\u0442\u0447\u0438\u043a Python", "salary_min": null, "salary_max": null, "salary_currency": null, "vacancy_link": "https://novosibirsk.hh.ru/vacancy/45434650", "site": "hh.ru"}, {"vacancy_name": "\u0420\u0430\u0437\u0440\u0430\u0431\u043e\u0442\u0447\u0438\u043a \u043d\u0430 Python \u0432 \u041b\u0430\u0432\u043a\u0443", "salary_min": null, "salary_max": null, "salary_currency": null, "vacancy_link": "https://novosibirsk.hh.ru/vacancy/45621261", "site": "hh.ru"}, {"vacancy_name": "Senior Python Backend Developer", "salary_min": null, "salary_max": null, "salary_currency": null, "vacancy_link": "https://novosibirsk.hh.ru/vacancy/40289680", "site": "hh.ru"}, {"vacancy_name": "Senior QA Automation Engineer (Python)", "salary_min": null, "salary_max": null, "salary_currency": null, "vacancy_link": "https://novosibirsk.hh.ru/vacancy/45904029", "site": "hh.ru"}, {"vacancy_name": "Python Developer", "salary_min": null, "salary_max": null, "salary_currency": null, "vacancy_link": "https://novosibirsk.hh.ru/vacancy/44954408", "site": "hh.ru"}, {"vacancy_name": "Senior Python \u043f\u0440\u043e\u0433\u0440\u0430\u043c\u043c\u0438\u0441\u0442", "salary_min": null, "salary_max": null, "salary_currency": null, "vacancy_link": "https://novosibirsk.hh.ru/vacancy/41607888", "site": "hh.ru"}, {"vacancy_name": "\u0420\u0430\u0437\u0440\u0430\u0431\u043e\u0442\u0447\u0438\u043a Python/Go", "salary_min": null, "salary_max": null, "salary_currency": null, "vacancy_link": "https://novosibirsk.hh.ru/vacancy/45538238", "site": "hh.ru"}, {"vacancy_name": "Python developer (Middle)", "salary_min": null, "salary_max": null, "salary_currency": null, "vacancy_link": "https://novosibirsk.hh.ru/vacancy/45662438", "site": "hh.ru"}, {"vacancy_name": "\u041f\u0440\u043e\u0433\u0440\u0430\u043c\u043c\u0438\u0441\u0442 Python", "salary_min": null, "salary_max": null, "salary_currency": null, "vacancy_link": "https://novosibirsk.hh.ru/vacancy/42571302", "site": "hh.ru"}, {"vacancy_name": "Python developer (Middle)", "salary_min": null, "salary_max": null, "salary_currency": null, "vacancy_link": "https://novosibirsk.hh.ru/vacancy/45662445", "site": "hh.ru"}, {"vacancy_name": "Middle Python Developer", "salary_min": null, "salary_max": null, "salary_currency": null, "vacancy_link": "https://novosibirsk.hh.ru/vacancy/44818284", "site": "hh.ru"}, {"vacancy_name": "\u041f\u0440\u043e\u0433\u0440\u0430\u043c\u043c\u0438\u0441\u0442-\u0440\u0430\u0437\u0440\u0430\u0431\u043e\u0442\u0447\u0438\u043a Java/Python", "salary_min": null, "salary_max": null, "salary_currency": null, "vacancy_link": "https://novosibirsk.hh.ru/vacancy/45504892", "site": "hh.ru"}, {"vacancy_name": "Python Middle \u0440\u0430\u0437\u0440\u0430\u0431\u043e\u0442\u0447\u0438\u043a", "salary_min": null, "salary_max": null, "salary_currency": null, "vacancy_link": "https://novosibirsk.hh.ru/vacancy/45648906", "site": "hh.ru"}, {"vacancy_name": "Python \u0420\u0430\u0437\u0440\u0430\u0431\u043e\u0442\u0447\u0438\u043a (\u0423\u0434\u0430\u043b\u0435\u043d\u043d\u043e)", "salary_min": null, "salary_max": null, "salary_currency": null, "vacancy_link": "https://novosibirsk.hh.ru/vacancy/45739799", "site": "hh.ru"}, {"vacancy_name": "Machine Learning Intern (Java/Python)", "salary_min": null, "salary_max": null, "salary_currency": null, "vacancy_link": "https://novosibirsk.hh.ru/vacancy/44780446", "site": "hh.ru"}, {"vacancy_name": "Junior Python Data Scientist", "salary_min": null, "salary_max": null, "salary_currency": null, "vacancy_link": "https://novosibirsk.hh.ru/vacancy/45581463", "site": "hh.ru"}, {"vacancy_name": "Python developer (Middle)", "salary_min": null, "salary_max": null, "salary_currency": null, "vacancy_link": "https://novosibirsk.hh.ru/vacancy/45662439", "site": "hh.ru"}, {"vacancy_name": "Senior Python \u0440\u0430\u0437\u0440\u0430\u0431\u043e\u0442\u0447\u0438\u043a \u0432 SberDevices (\u0438\u043d\u0444\u0440\u0430\u0441\u0442\u0440\u0443\u043a\u0442\u0443\u0440\u0430 \u043f\u043e\u0438\u0441\u043a\u0430)", "salary_min": null, "salary_max": null, "salary_currency": null, "vacancy_link": "https://novosibirsk.hh.ru/vacancy/44205479", "site": "hh.ru"}, {"vacancy_name": "Python \u0440\u0430\u0437\u0440\u0430\u0431\u043e\u0442\u0447\u0438\u043a", "salary_min": null, "salary_max": null, "salary_currency": null, "vacancy_link": "https://novosibirsk.hh.ru/vacancy/45652745", "site": "hh.ru"}, {"vacancy_name": "Machine Learning Team Lead (Java/Python)", "salary_min": null, "salary_max": null, "salary_currency": null, "vacancy_link": "https://novosibirsk.hh.ru/vacancy/44908548", "site": "hh.ru"}, {"vacancy_name": "Python developer", "salary_min": null, "salary_max": null, "salary_currency": null, "vacancy_link": "https://novosibirsk.hh.ru/vacancy/45596158", "site": "hh.ru"}, {"vacancy_name": "Python developer (Middle)", "salary_min": null, "salary_max": null, "salary_currency": null, "vacancy_link": "https://novosibirsk.hh.ru/vacancy/45662440", "site": "hh.ru"}, {"vacancy_name": "Senior Python Developer", "salary_min": null, "salary_max": null, "salary_currency": null, "vacancy_link": "https://novosibirsk.hh.ru/vacancy/43968966", "site": "hh.ru"}, {"vacancy_name": "Middle Python Developer", "salary_min": null, "salary_max": null, "salary_currency": null, "vacancy_link": "https://novosibirsk.hh.ru/vacancy/36606581", "site": "hh.ru"}, {"vacancy_name": "Senior Python developer || Remote", "salary_min": null, "salary_max": null, "salary_currency": null, "vacancy_link": "https://novosibirsk.hh.ru/vacancy/45487890", "site": "hh.ru"}, {"vacancy_name": "\u0420\u0430\u0437\u0440\u0430\u0431\u043e\u0442\u0447\u0438\u043a Python", "salary_min": null, "salary_max": null, "salary_currency": null, "vacancy_link": "https://novosibirsk.hh.ru/vacancy/45722662", "site": "hh.ru"}, {"vacancy_name": "Backend developer Python", "salary_min": null, "salary_max": null, "salary_currency": null, "vacancy_link": "https://novosibirsk.hh.ru/vacancy/44644831", "site": "hh.ru"}, {"vacancy_name": "Python \u0440\u0430\u0437\u0440\u0430\u0431\u043e\u0442\u0447\u0438\u043a", "salary_min": null, "salary_max": null, "salary_currency": null, "vacancy_link": "https://novosibirsk.hh.ru/vacancy/45558758", "site": "hh.ru"}, {"vacancy_name": "JavaScript/Python developer SberDevices", "salary_min": null, "salary_max": null, "salary_currency": null, "vacancy_link": "https://novosibirsk.hh.ru/vacancy/44048072", "site": "hh.ru"}, {"vacancy_name": "\u041f\u0440\u043e\u0433\u0440\u0430\u043c\u043c\u0438\u0441\u0442 Python", "salary_min": null, "salary_max": null, "salary_currency": null, "vacancy_link": "https://novosibirsk.hh.ru/vacancy/34847333", "site": "hh.ru"}, {"vacancy_name": "Python \u0440\u0430\u0437\u0440\u0430\u0431\u043e\u0442\u0447\u0438\u043a", "salary_min": null, "salary_max": null, "salary_currency": null, "vacancy_link": "https://novosibirsk.hh.ru/vacancy/45558804", "site": "hh.ru"}, {"vacancy_name": "Junior/middle python developer", "salary_min": null, "salary_max": null, "salary_currency": null, "vacancy_link": "https://novosibirsk.hh.ru/vacancy/45518865", "site": "hh.ru"}, {"vacancy_name": "Python \u0440\u0430\u0437\u0440\u0430\u0431\u043e\u0442\u0447\u0438\u043a", "salary_min": null, "salary_max": null, "salary_currency": null, "vacancy_link": "https://novosibirsk.hh.ru/vacancy/45558786", "site": "hh.ru"}, {"vacancy_name": "\u041f\u0440\u043e\u0433\u0440\u0430\u043c\u043c\u0438\u0441\u0442 Python", "salary_min": null, "salary_max": null, "salary_currency": null, "vacancy_link": "https://novosibirsk.hh.ru/vacancy/45612943", "site": "hh.ru"}, {"vacancy_name": "\u0420\u0430\u0437\u0440\u0430\u0431\u043e\u0442\u0447\u0438\u043a Python (\u043c\u043e\u0436\u043d\u043e \u0443\u0434\u0430\u043b\u0435\u043d\u043d\u043e)", "salary_min": null, "salary_max": null, "salary_currency": null, "vacancy_link": "https://novosibirsk.hh.ru/vacancy/45559087", "site": "hh.ru"}, {"vacancy_name": "\u0421\u0442\u0430\u0440\u0448\u0438\u0439 \u0440\u0430\u0437\u0440\u0430\u0431\u043e\u0442\u0447\u0438\u043a Python", "salary_min": null, "salary_max": null, "salary_currency": null, "vacancy_link": "https://novosibirsk.hh.ru/vacancy/42772685", "site": "hh.ru"}, {"vacancy_name": "ML/Backend Engineer (Python)", "salary_min": null, "salary_max": null, "salary_currency": null, "vacancy_link": "https://novosibirsk.hh.ru/vacancy/45776160", "site": "hh.ru"}, {"vacancy_name": "Python developer (\u0437\u0430\u0449\u0438\u0442\u0430 \u043e\u0442 DDoS-\u0430\u0442\u0430\u043a)", "salary_min": null, "salary_max": null, "salary_currency": null, "vacancy_link": "https://novosibirsk.hh.ru/vacancy/44074460", "site": "hh.ru"}, {"vacancy_name": "Python \u0440\u0430\u0437\u0440\u0430\u0431\u043e\u0442\u0447\u0438\u043a", "salary_min": null, "salary_max": null, "salary_currency": null, "vacancy_link": "https://novosibirsk.hh.ru/vacancy/45601287", "site": "hh.ru"}, {"vacancy_name": "\u0420\u0430\u0437\u0440\u0430\u0431\u043e\u0442\u0447\u0438\u043a Python/Python Developer", "salary_min": null, "salary_max": null, "salary_currency": null, "vacancy_link": "https://novosibirsk.hh.ru/vacancy/41099265", "site": "hh.ru"}, {"vacancy_name": "Python Developer (\u0440\u0430\u0437\u0440\u0430\u0431\u043e\u0442\u043a\u0430 \u043f\u043b\u0430\u0442\u0435\u0436\u043d\u044b\u0445 \u0441\u0435\u0440\u0432\u0438\u0441\u043e\u0432)", "salary_min": null, "salary_max": null, "salary_currency": null, "vacancy_link": "https://novosibirsk.hh.ru/vacancy/44293844", "site": "hh.ru"}, {"vacancy_name": "Middle Python developer", "salary_min": null, "salary_max": null, "salary_currency": null, "vacancy_link": "https://novosibirsk.hh.ru/vacancy/43855787", "site": "hh.ru"}, {"vacancy_name": "\u041f\u0440\u043e\u0433\u0440\u0430\u043c\u043c\u0438\u0441\u0442 Python", "salary_min": null, "salary_max": null, "salary_currency": null, "vacancy_link": "https://novosibirsk.hh.ru/vacancy/41772323", "site": "hh.ru"}, {"vacancy_name": "Big Data Developer with Python / Spark / AWS", "salary_min": null, "salary_max": null, "salary_currency": null, "vacancy_link": "https://novosibirsk.hh.ru/vacancy/40577198", "site": "hh.ru"}, {"vacancy_name": "Python Middle Developer", "salary_min": null, "salary_max": null, "salary_currency": null, "vacancy_link": "https://novosibirsk.hh.ru/vacancy/42512310", "site": "hh.ru"}, {"vacancy_name": "Python developer (middle)", "salary_min": null, "salary_max": null, "salary_currency": null, "vacancy_link": "https://novosibirsk.hh.ru/vacancy/38792841", "site": "hh.ru"}, {"vacancy_name": "\u0412\u0435\u0434\u0443\u0449\u0438\u0439 \u0440\u0430\u0437\u0440\u0430\u0431\u043e\u0442\u0447\u0438\u043a Python", "salary_min": null, "salary_max": null, "salary_currency": null, "vacancy_link": "https://novosibirsk.hh.ru/vacancy/45451940", "site": "hh.ru"}, {"vacancy_name": "Python \u0440\u0430\u0437\u0440\u0430\u0431\u043e\u0442\u0447\u0438\u043a", "salary_min": null, "salary_max": null, "salary_currency": null, "vacancy_link": "https://novosibirsk.hh.ru/vacancy/45558758", "site": "hh.ru"}, {"vacancy_name": "Backend-\u0440\u0430\u0437\u0440\u0430\u0431\u043e\u0442\u0447\u0438\u043a (Python)", "salary_min": null, "salary_max": null, "salary_currency": null, "vacancy_link": "https://novosibirsk.hh.ru/vacancy/45526389", "site": "hh.ru"}, {"vacancy_name": "\u0422\u0435\u0441\u0442\u0438\u0440\u043e\u0432\u0449\u0438\u043a (Python)", "salary_min": null, "salary_max": null, "salary_currency": null, "vacancy_link": "https://novosibirsk.hh.ru/vacancy/45450423", "site": "hh.ru"}, {"vacancy_name": "Python \u0440\u0430\u0437\u0440\u0430\u0431\u043e\u0442\u0447\u0438\u043a (\u0443\u0434\u0430\u043b\u0435\u043d\u043d\u043e)", "salary_min": null, "salary_max": null, "salary_currency": null, "vacancy_link": "https://novosibirsk.hh.ru/vacancy/45457290", "site": "hh.ru"}, {"vacancy_name": "Data Engineer (Python)", "salary_min": null, "salary_max": null, "salary_currency": null, "vacancy_link": "https://novosibirsk.hh.ru/vacancy/45471066", "site": "hh.ru"}, {"vacancy_name": "Senior python \u0440\u0430\u0437\u0440\u0430\u0431\u043e\u0442\u0447\u0438\u043a", "salary_min": null, "salary_max": null, "salary_currency": null, "vacancy_link": "https://novosibirsk.hh.ru/vacancy/44489869", "site": "hh.ru"}, {"vacancy_name": "Python Developer (Extranet Team)", "salary_min": null, "salary_max": null, "salary_currency": null, "vacancy_link": "https://novosibirsk.hh.ru/vacancy/45620118", "site": "hh.ru"}, {"vacancy_name": "Python \u0440\u0430\u0437\u0440\u0430\u0431\u043e\u0442\u0447\u0438\u043a", "salary_min": null, "salary_max": null, "salary_currency": null, "vacancy_link": "https://novosibirsk.hh.ru/vacancy/45558786", "site": "hh.ru"}, {"vacancy_name": "Test Automation Engineer / Python developer in Autotest", "salary_min": null, "salary_max": null, "salary_currency": null, "vacancy_link": "https://novosibirsk.hh.ru/vacancy/45573605", "site": "hh.ru"}, {"vacancy_name": "Middle Backend Python/Django \u0440\u0430\u0437\u0440\u0430\u0431\u043e\u0442\u0447\u0438\u043a (\u0443\u0434\u0430\u043b\u0451\u043d\u043d\u043e)", "salary_min": null, "salary_max": null, "salary_currency": null, "vacancy_link": "https://novosibirsk.hh.ru/vacancy/44362483", "site": "hh.ru"}, {"vacancy_name": "Python \u0440\u0430\u0437\u0440\u0430\u0431\u043e\u0442\u0447\u0438\u043a (backend)", "salary_min": null, "salary_max": null, "salary_currency": null, "vacancy_link": "https://novosibirsk.hh.ru/vacancy/38109909", "site": "hh.ru"}, {"vacancy_name": "\u041f\u0440\u043e\u0433\u0440\u0430\u043c\u043c\u0438\u0441\u0442 Python", "salary_min": null, "salary_max": null, "salary_currency": null, "vacancy_link": "https://novosibirsk.hh.ru/vacancy/45466524", "site": "hh.ru"}, {"vacancy_name": "\u041f\u0440\u043e\u0433\u0440\u0430\u043c\u043c\u0438\u0441\u0442-\u0430\u043d\u0430\u043b\u0438\u0442\u0438\u043a Python", "salary_min": null, "salary_max": null, "salary_currency": null, "vacancy_link": "https://novosibirsk.hh.ru/vacancy/42007370", "site": "hh.ru"}, {"vacancy_name": "Python \u0440\u0430\u0437\u0440\u0430\u0431\u043e\u0442\u0447\u0438\u043a", "salary_min": null, "salary_max": null, "salary_currency": null, "vacancy_link": "https://novosibirsk.hh.ru/vacancy/43505141", "site": "hh.ru"}, {"vacancy_name": "Python \u0440\u0430\u0437\u0440\u0430\u0431\u043e\u0442\u0447\u0438\u043a", "salary_min": null, "salary_max": null, "salary_currency": null, "vacancy_link": "https://novosibirsk.hh.ru/vacancy/44557193", "site": "hh.ru"}, {"vacancy_name": "Python \u0420\u0430\u0437\u0440\u0430\u0431\u043e\u0442\u0447\u0438\u043a Full Stack (\u0444\u0443\u043b\u043b\u0441\u0442\u044d\u043a)", "salary_min": null, "salary_max": null, "salary_currency": null, "vacancy_link": "https://novosibirsk.hh.ru/vacancy/45576389", "site": "hh.ru"}, {"vacancy_name": "Python Developer", "salary_min": null, "salary_max": null, "salary_currency": null, "vacancy_link": "https://novosibirsk.hh.ru/vacancy/45504301", "site": "hh.ru"}, {"vacancy_name": "\u0420\u0430\u0437\u0440\u0430\u0431\u043e\u0442\u0447\u0438\u043a Android / Python", "salary_min": null, "salary_max": null, "salary_currency": null, "vacancy_link": "https://novosibirsk.hh.ru/vacancy/44753176", "site": "hh.ru"}, {"vacancy_name": "Python Developer", "salary_min": null, "salary_max": null, "salary_currency": null, "vacancy_link": "https://novosibirsk.hh.ru/vacancy/43641477", "site": "hh.ru"}, {"vacancy_name": "Python Developer (gamedev)", "salary_min": null, "salary_max": null, "salary_currency": null, "vacancy_link": "https://novosibirsk.hh.ru/vacancy/42804062", "site": "hh.ru"}, {"vacancy_name": "Junior Data Scientist/Python \u0440\u0430\u0437\u0440\u0430\u0431\u043e\u0442\u0447\u0438\u043a", "salary_min": null, "salary_max": null, "salary_currency": null, "vacancy_link": "https://novosibirsk.hh.ru/vacancy/45533007", "site": "hh.ru"}, {"vacancy_name": "\u041f\u0440\u043e\u0433\u0440\u0430\u043c\u043c\u0438\u0441\u0442 Python", "salary_min": null, "salary_max": null, "salary_currency": null, "vacancy_link": "https://novosibirsk.hh.ru/vacancy/43034540", "site": "hh.ru"}, {"vacancy_name": "\u0420\u0430\u0437\u0440\u0430\u0431\u043e\u0442\u0447\u0438\u043a Python Django (REST)", "salary_min": null, "salary_max": null, "salary_currency": null, "vacancy_link": "https://novosibirsk.hh.ru/vacancy/45315584", "site": "hh.ru"}, {"vacancy_name": "\u0420\u0430\u0437\u0440\u0430\u0431\u043e\u0442\u0447\u0438\u043a RPA (Python)", "salary_min": null, "salary_max": null, "salary_currency": null, "vacancy_link": "https://novosibirsk.hh.ru/vacancy/45504887", "site": "hh.ru"}, {"vacancy_name": "Python developer", "salary_min": null, "salary_max": null, "salary_currency": null, "vacancy_link": "https://novosibirsk.hh.ru/vacancy/45355945", "site": "hh.ru"}, {"vacancy_name": "Python \u0440\u0430\u0437\u0440\u0430\u0431\u043e\u0442\u0447\u0438\u043a / python developer", "salary_min": null, "salary_max": null, "salary_currency": null, "vacancy_link": "https://novosibirsk.hh.ru/vacancy/45366201", "site": "hh.ru"}, {"vacancy_name": "Python Backend Developer (Middle/Remote)", "salary_min": null, "salary_max": null, "salary_currency": null, "vacancy_link": "https://novosibirsk.hh.ru/vacancy/45571453", "site": "hh.ru"}, {"vacancy_name": "Python/Django \u0440\u0430\u0437\u0440\u0430\u0431\u043e\u0442\u0447\u0438\u043a (\u0441\u0442\u0430\u0440\u0442 \u043f\u0440\u043e\u0435\u043a\u0442\u0430)", "salary_min": null, "salary_max": null, "salary_currency": null, "vacancy_link": "https://novosibirsk.hh.ru/vacancy/45411664", "site": "hh.ru"}, {"vacancy_name": "BackEnd Lead Python", "salary_min": null, "salary_max": null, "salary_currency": null, "vacancy_link": "https://novosibirsk.hh.ru/vacancy/45458021", "site": "hh.ru"}, {"vacancy_name": "Python \u0440\u0430\u0437\u0440\u0430\u0431\u043e\u0442\u0447\u0438\u043a", "salary_min": null, "salary_max": null, "salary_currency": null, "vacancy_link": "https://novosibirsk.hh.ru/vacancy/45558605", "site": "hh.ru"}, {"vacancy_name": "\u0412\u0435\u0434\u0443\u0449\u0438\u0439 \u043f\u0440\u043e\u0433\u0440\u0430\u043c\u043c\u0438\u0441\u0442 Python", "salary_min": null, "salary_max": null, "salary_currency": null, "vacancy_link": "https://novosibirsk.hh.ru/vacancy/45396237", "site": "hh.ru"}, {"vacancy_name": "Python \u0440\u0430\u0437\u0440\u0430\u0431\u043e\u0442\u0447\u0438\u043a", "salary_min": null, "salary_max": null, "salary_currency": null, "vacancy_link": "https://novosibirsk.hh.ru/vacancy/45347984", "site": "hh.ru"}, {"vacancy_name": "\u0420\u0430\u0437\u0440\u0430\u0431\u043e\u0442\u0447\u0438\u043a Python", "salary_min": null, "salary_max": null, "salary_currency": null, "vacancy_link": "https://novosibirsk.hh.ru/vacancy/45453462", "site": "hh.ru"}, {"vacancy_name": "Python Developer for Big Data (remote)", "salary_min": null, "salary_max": null, "salary_currency": null, "vacancy_link": "https://novosibirsk.hh.ru/vacancy/45338342", "site": "hh.ru"}, {"vacancy_name": "\u0420\u0430\u0437\u0440\u0430\u0431\u043e\u0442\u0447\u0438\u043a Python / Python developer", "salary_min": null, "salary_max": null, "salary_currency": null, "vacancy_link": "https://novosibirsk.hh.ru/vacancy/45340960", "site": "hh.ru"}, {"vacancy_name": "Senior Python developer", "salary_min": null, "salary_max": null, "salary_currency": null, "vacancy_link": "https://novosibirsk.hh.ru/vacancy/45606900", "site": "hh.ru"}, {"vacancy_name": "\u0421\u0442\u0430\u0440\u0448\u0438\u0439 \u0440\u0430\u0437\u0440\u0430\u0431\u043e\u0442\u0447\u0438\u043a Python", "salary_min": null, "salary_max": null, "salary_currency": null, "vacancy_link": "https://novosibirsk.hh.ru/vacancy/42772685", "site": "hh.ru"}, {"vacancy_name": "Python/Golang \u0440\u0430\u0437\u0440\u0430\u0431\u043e\u0442\u0447\u0438\u043a", "salary_min": null, "salary_max": null, "salary_currency": null, "vacancy_link": "https://novosibirsk.hh.ru/vacancy/45142522", "site": "hh.ru"}, {"vacancy_name": "Back-end Python/Django \u0440\u0430\u0437\u0440\u0430\u0431\u043e\u0442\u0447\u0438\u043a", "salary_min": null, "salary_max": null, "salary_currency": null, "vacancy_link": "https://novosibirsk.hh.ru/vacancy/45349145", "site": "hh.ru"}, {"vacancy_name": "Python \u0440\u0430\u0437\u0440\u0430\u0431\u043e\u0442\u0447\u0438\u043a (SberWorks)", "salary_min": null, "salary_max": null, "salary_currency": null, "vacancy_link": "https://novosibirsk.hh.ru/vacancy/43760879", "site": "hh.ru"}, {"vacancy_name": "\u0420\u0430\u0437\u0440\u0430\u0431\u043e\u0442\u0447\u0438\u043a Python", "salary_min": null, "salary_max": null, "salary_currency": null, "vacancy_link": "https://novosibirsk.hh.ru/vacancy/45297056", "site": "hh.ru"}, {"vacancy_name": "Middle+/Senior Python \u0440\u0430\u0437\u0440\u0430\u0431\u043e\u0442\u0447\u0438\u043a (\u0443\u0434\u0430\u043b\u0435\u043d\u043d\u043e)", "salary_min": null, "salary_max": null, "salary_currency": null, "vacancy_link": "https://novosibirsk.hh.ru/vacancy/39339342", "site": "hh.ru"}, {"vacancy_name": "Python developer with AWS expertise", "salary_min": null, "salary_max": null, "salary_currency": null, "vacancy_link": "https://novosibirsk.hh.ru/vacancy/44778867", "site": "hh.ru"}, {"vacancy_name": "Python Middle Developer", "salary_min": null, "salary_max": null, "salary_currency": null, "vacancy_link": "https://novosibirsk.hh.ru/vacancy/44742832", "site": "hh.ru"}, {"vacancy_name": "\u0420\u0430\u0437\u0440\u0430\u0431\u043e\u0442\u0447\u0438\u043a Python (Senior, Principal)", "salary_min": null, "salary_max": null, "salary_currency": null, "vacancy_link": "https://novosibirsk.hh.ru/vacancy/44522651", "site": "hh.ru"}, {"vacancy_name": "Backend \u0440\u0430\u0437\u0440\u0430\u0431\u043e\u0442\u0447\u0438\u043a Python", "salary_min": null, "salary_max": null, "salary_currency": null, "vacancy_link": "https://novosibirsk.hh.ru/vacancy/45274514", "site": "hh.ru"}, {"vacancy_name": "Python Team Lead", "salary_min": null, "salary_max": null, "salary_currency": null, "vacancy_link": "https://novosibirsk.hh.ru/vacancy/45368090", "site": "hh.ru"}, {"vacancy_name": "Senior Fullstack Engineer (Python, Django, React)", "salary_min": null, "salary_max": null, "salary_currency": null, "vacancy_link": "https://novosibirsk.hh.ru/vacancy/45728058", "site": "hh.ru"}, {"vacancy_name": "Middle Python-\u0440\u0430\u0437\u0440\u0430\u0431\u043e\u0442\u0447\u0438\u043a", "salary_min": null, "salary_max": null, "salary_currency": null, "vacancy_link": "https://novosibirsk.hh.ru/vacancy/43340557", "site": "hh.ru"}, {"vacancy_name": "Python Developer", "salary_min": null, "salary_max": null, "salary_currency": null, "vacancy_link": "https://novosibirsk.hh.ru/vacancy/45236078", "site": "hh.ru"}, {"vacancy_name": "\u0411\u044d\u043a\u0435\u043d\u0434-\u0440\u0430\u0437\u0440\u0430\u0431\u043e\u0442\u0447\u0438\u043a (Python)", "salary_min": null, "salary_max": null, "salary_currency": null, "vacancy_link": "https://novosibirsk.hh.ru/vacancy/45244578", "site": "hh.ru"}, {"vacancy_name": "\u0418\u043d\u0436\u0435\u043d\u0435\u0440-\u043f\u0440\u043e\u0433\u0440\u0430\u043c\u043c\u0438\u0441\u0442 Python/Django", "salary_min": null, "salary_max": null, "salary_currency": null, "vacancy_link": "https://novosibirsk.hh.ru/vacancy/45359229", "site": "hh.ru"}, {"vacancy_name": "Middle/Senior Python-\u0440\u0430\u0437\u0440\u0430\u0431\u043e\u0442\u0447\u0438\u043a", "salary_min": null, "salary_max": null, "salary_currency": null, "vacancy_link": "https://novosibirsk.hh.ru/vacancy/45579915", "site": "hh.ru"}, {"vacancy_name": "\u041f\u0440\u043e\u0433\u0440\u0430\u043c\u043c\u0438\u0441\u0442 Python", "salary_min": null, "salary_max": null, "salary_currency": null, "vacancy_link": "https://novosibirsk.hh.ru/vacancy/45792016", "site": "hh.ru"}, {"vacancy_name": "Python-\u043f\u0440\u043e\u0433\u0440\u0430\u043c\u043c\u0438\u0441\u0442 (\u0420\u0430\u0437\u0440\u0430\u0431\u043e\u0442\u0447\u0438\u043a)", "salary_min": null, "salary_max": null, "salary_currency": null, "vacancy_link": "https://novosibirsk.hh.ru/vacancy/37406138", "site": "hh.ru"}, {"vacancy_name": "\u041f\u0440\u0435\u043f\u043e\u0434\u0430\u0432\u0430\u0442\u0435\u043b\u044c \u043f\u043e Python", "salary_min": null, "salary_max": null, "salary_currency": null, "vacancy_link": "https://novosibirsk.hh.ru/vacancy/45784581", "site": "hh.ru"}, {"vacancy_name": "Python Developer (Backend)", "salary_min": null, "salary_max": null, "salary_currency": null, "vacancy_link": "https://novosibirsk.hh.ru/vacancy/45744838", "site": "hh.ru"}, {"vacancy_name": "Senior Python Developer", "salary_min": null, "salary_max": null, "salary_currency": null, "vacancy_link": "https://novosibirsk.hh.ru/vacancy/45797309", "site": "hh.ru"}, {"vacancy_name": "Python Developer", "salary_min": null, "salary_max": null, "salary_currency": null, "vacancy_link": "https://novosibirsk.hh.ru/vacancy/45818687", "site": "hh.ru"}, {"vacancy_name": "\u041f\u0440\u0435\u043f\u043e\u0434\u0430\u0432\u0430\u0442\u0435\u043b\u044c \u0412\u0435\u0431-\u0440\u0430\u0437\u0440\u0430\u0431\u043e\u0442\u043a\u0430 \u0438 Python (\u0431\u0430\u0437\u0430)", "salary_min": null, "salary_max": null, "salary_currency": null, "vacancy_link": "https://novosibirsk.hh.ru/vacancy/45759617", "site": "hh.ru"}, {"vacancy_name": "Python Developer", "salary_min": null, "salary_max": null, "salary_currency": null, "vacancy_link": "https://novosibirsk.hh.ru/vacancy/45748012", "site": "hh.ru"}, {"vacancy_name": "\u0418\u043d\u0436\u0435\u043d\u0435\u0440-\u043f\u0440\u043e\u0433\u0440\u0430\u043c\u043c\u0438\u0441\u0442 Python", "salary_min": null, "salary_max": null, "salary_currency": null, "vacancy_link": "https://novosibirsk.hh.ru/vacancy/45591348", "site": "hh.ru"}, {"vacancy_name": "Python Developer", "salary_min": null, "salary_max": null, "salary_currency": null, "vacancy_link": "https://novosibirsk.hh.ru/vacancy/45431390", "site": "hh.ru"}, {"vacancy_name": "Python developer/Remote", "salary_min": null, "salary_max": null, "salary_currency": null, "vacancy_link": "https://novosibirsk.hh.ru/vacancy/45419924", "site": "hh.ru"}, {"vacancy_name": "Python Back-end developer", "salary_min": null, "salary_max": null, "salary_currency": null, "vacancy_link": "https://novosibirsk.hh.ru/vacancy/45634159", "site": "hh.ru"}, {"vacancy_name": "Senior Python developer (Django)", "salary_min": null, "salary_max": null, "salary_currency": null, "vacancy_link": "https://novosibirsk.hh.ru/vacancy/45639617", "site": "hh.ru"}, {"vacancy_name": "\u041f\u0440\u0435\u043f\u043e\u0434\u0430\u0432\u0430\u0442\u0435\u043b\u044c Python", "salary_min": null, "salary_max": null, "salary_currency": null, "vacancy_link": "https://novosibirsk.hh.ru/vacancy/45655857", "site": "hh.ru"}, {"vacancy_name": "\u041f\u0440\u0435\u043f\u043e\u0434\u0430\u0432\u0430\u0442\u0435\u043b\u044c Python", "salary_min": null, "salary_max": null, "salary_currency": null, "vacancy_link": "https://novosibirsk.hh.ru/vacancy/45340635", "site": "hh.ru"}, {"vacancy_name": "Python/Django Web Developer", "salary_min": null, "salary_max": null, "salary_currency": null, "vacancy_link": "https://novosibirsk.hh.ru/vacancy/45345448", "site": "hh.ru"}, {"vacancy_name": "Python Developer", "salary_min": null, "salary_max": null, "salary_currency": null, "vacancy_link": "https://novosibirsk.hh.ru/vacancy/45317692", "site": "hh.ru"}, {"vacancy_name": "Python/Django Web Developer", "salary_min": null, "salary_max": null, "salary_currency": null, "vacancy_link": "https://novosibirsk.hh.ru/vacancy/45345449", "site": "hh.ru"}, {"vacancy_name": "\u041f\u0440\u043e\u0433\u0440\u0430\u043c\u043c\u0438\u0441\u0442: Angular, Flutter, Python", "salary_min": null, "salary_max": null, "salary_currency": null, "vacancy_link": "https://novosibirsk.hh.ru/vacancy/45529580", "site": "hh.ru"}, {"vacancy_name": "Fullstack Middle Python Developer", "salary_min": null, "salary_max": null, "salary_currency": null, "vacancy_link": "https://novosibirsk.hh.ru/vacancy/45340877", "site": "hh.ru"}, {"vacancy_name": "Tech Lead with Python Experience, Financial Software Solutions", "salary_min": null, "salary_max": null, "salary_currency": null, "vacancy_link": "https://novosibirsk.hh.ru/vacancy/44845594", "site": "hh.ru"}, {"vacancy_name": "Senior Python Developer, Media Distribution Platform", "salary_min": null, "salary_max": null, "salary_currency": null, "vacancy_link": "https://novosibirsk.hh.ru/vacancy/44312247", "site": "hh.ru"}, {"vacancy_name": "QA Automation Engineer / \u0410\u0432\u0442\u043e\u0442\u0435\u0441\u0442\u0438\u0440\u043e\u0432\u0449\u0438\u043a (Python)", "salary_min": null, "salary_max": null, "salary_currency": null, "vacancy_link": "https://novosibirsk.hh.ru/vacancy/43703298", "site": "hh.ru"}, {"vacancy_name": "QA Automation Engineer / \u0410\u0432\u0442\u043e\u0442\u0435\u0441\u0442\u0438\u0440\u043e\u0432\u0449\u0438\u043a (Python)", "salary_min": null, "salary_max": null, "salary_currency": null, "vacancy_link": "https://novosibirsk.hh.ru/vacancy/43703303", "site": "hh.ru"}, {"vacancy_name": "Python backend-\u0440\u0430\u0437\u0440\u0430\u0431\u043e\u0442\u0447\u0438\u043a (IT-\u043a\u043e\u043c\u043f\u0430\u043d\u0438\u044f)", "salary_min": null, "salary_max": null, "salary_currency": null, "vacancy_link": "https://novosibirsk.hh.ru/vacancy/45061368", "site": "hh.ru"}, {"vacancy_name": "\u0420\u0430\u0437\u0440\u0430\u0431\u043e\u0442\u0447\u0438\u043a \u0432\u044b\u0441\u043e\u043a\u043e\u043f\u0440\u043e\u0438\u0437\u0432\u043e\u0434\u0438\u0442\u0435\u043b\u044c\u043d\u044b\u0445 C++/Python \u0441\u0438\u0441\u0442\u0435\u043c", "salary_min": null, "salary_max": null, "salary_currency": null, "vacancy_link": "https://novosibirsk.hh.ru/vacancy/45908150", "site": "hh.ru"}, {"vacancy_name": "\u0420\u0430\u0437\u0440\u0430\u0431\u043e\u0442\u0447\u0438\u043a Python (Senior Developer/middle)", "salary_min": null, "salary_max": null, "salary_currency": null, "vacancy_link": "https://novosibirsk.hh.ru/vacancy/45175928", "site": "hh.ru"}, {"vacancy_name": "QA Automation (Python) Engineer, Crypto Security Solution", "salary_min": null, "salary_max": null, "salary_currency": null, "vacancy_link": "https://novosibirsk.hh.ru/vacancy/45908822", "site": "hh.ru"}, {"vacancy_name": "Senior Python Developer, Media Distribution Platform", "salary_min": null, "salary_max": null, "salary_currency": null, "vacancy_link": "https://novosibirsk.hh.ru/vacancy/45568061", "site": "hh.ru"}, {"vacancy_name": "\u041f\u0440\u043e\u0433\u0440\u0430\u043c\u043c\u0438\u0441\u0442 Python, API-\u0438\u043d\u0442\u0435\u0433\u0440\u0430\u0446\u0438\u0438 \u0441 \u0411\u0438\u0442\u0440\u0438\u043a\u044124", "salary_min": null, "salary_max": null, "salary_currency": null, "vacancy_link": "https://novosibirsk.hh.ru/vacancy/43315122", "site": "hh.ru"}, {"vacancy_name": "QA Automation Engineer (Python)/\u0412\u0435\u0434\u0443\u0449\u0438\u0439 \u0442\u0435\u0441\u0442\u0438\u0440\u043e\u0432\u0449\u0438\u043a \u041f\u041e", "salary_min": null, "salary_max": null, "salary_currency": null, "vacancy_link": "https://novosibirsk.hh.ru/vacancy/45881683", "site": "hh.ru"}, {"vacancy_name": "\u0420\u0430\u0437\u0440\u0430\u0431\u043e\u0442\u0447\u0438\u043a \u0438\u043d\u0444\u043e\u0440\u043c\u0430\u0446\u0438\u043e\u043d\u043d\u044b\u0445 \u0441\u0438\u0441\u0442\u0435\u043c \u043d\u0430 Oracle/python", "salary_min": null, "salary_max": null, "salary_currency": null, "vacancy_link": "https://novosibirsk.hh.ru/vacancy/44041462", "site": "hh.ru"}, {"vacancy_name": "\u0418\u043d\u0436\u0435\u043d\u0435\u0440 \u043f\u043e \u0430\u0432\u0442\u043e\u0442\u0435\u0441\u0442\u0438\u0440\u043e\u0432\u0430\u043d\u0438\u044e \u0432 \u041b\u0430\u0432\u043a\u0443 (Python)", "salary_min": null, "salary_max": null, "salary_currency": null, "vacancy_link": "https://novosibirsk.hh.ru/vacancy/45888946", "site": "hh.ru"}, {"vacancy_name": "\u0420\u0430\u0437\u0440\u0430\u0431\u043e\u0442\u0447\u0438\u043a \u0441\u0440\u0435\u0434\u0441\u0442\u0432 \u0430\u0432\u0442\u043e\u043c\u0430\u0442\u0438\u0437\u0430\u0446\u0438\u0438 (Python)", "salary_min": null, "salary_max": null, "salary_currency": null, "vacancy_link": "https://novosibirsk.hh.ru/vacancy/45889797", "site": "hh.ru"}, {"vacancy_name": "Fullstack-\u0440\u0430\u0437\u0440\u0430\u0431\u043e\u0442\u0447\u0438\u043a (\u0443\u043f\u043e\u0440 \u043d\u0430 \u0440\u0430\u0437\u0440\u0430\u0431\u043e\u0442\u043a\u0443 \u043d\u0430 Python \u0438 \u0430\u0440\u0445\u0438\u0442\u0435\u043a\u0442\u0443\u0440\u0443)", "salary_min": null, "salary_max": null, "salary_currency": null, "vacancy_link": "https://novosibirsk.hh.ru/vacancy/45888625", "site": "hh.ru"}, {"vacancy_name": "Fullstack-\u0440\u0430\u0437\u0440\u0430\u0431\u043e\u0442\u0447\u0438\u043a (\u0443\u043f\u043e\u0440 \u043d\u0430 \u0440\u0430\u0437\u0440\u0430\u0431\u043e\u0442\u043a\u0443 \u043d\u0430 Python \u0438 \u0430\u0440\u0445\u0438\u0442\u0435\u043a\u0442\u0443\u0440\u0443)", "salary_min": null, "salary_max": null, "salary_currency": null, "vacancy_link": "https://novosibirsk.hh.ru/vacancy/45888624", "site": "hh.ru"}, {"vacancy_name": "Fullstack-\u0440\u0430\u0437\u0440\u0430\u0431\u043e\u0442\u0447\u0438\u043a (\u0443\u043f\u043e\u0440 \u043d\u0430 \u0440\u0430\u0437\u0440\u0430\u0431\u043e\u0442\u043a\u0443 \u043d\u0430 Python \u0438 \u0430\u0440\u0445\u0438\u0442\u0435\u043a\u0442\u0443\u0440\u0443)", "salary_min": null, "salary_max": null, "salary_currency": null, "vacancy_link": "https://novosibirsk.hh.ru/vacancy/45888623", "site": "hh.ru"}, {"vacancy_name": "\u041c\u0435\u0442\u043e\u0434\u0438\u0441\u0442-\u043f\u0440\u0435\u043f\u043e\u0434\u0430\u0432\u0430\u0442\u0435\u043b\u044c \u043f\u043e \u043a\u0443\u0440\u0441\u0443 Python", "salary_min": null, "salary_max": null, "salary_currency": null, "vacancy_link": "https://novosibirsk.hh.ru/vacancy/45886397", "site": "hh.ru"}, {"vacancy_name": "Fullstack-\u0440\u0430\u0437\u0440\u0430\u0431\u043e\u0442\u0447\u0438\u043a (\u0443\u043f\u043e\u0440 \u043d\u0430 \u0440\u0430\u0437\u0440\u0430\u0431\u043e\u0442\u043a\u0443 \u043d\u0430 Python \u0438 \u0430\u0440\u0445\u0438\u0442\u0435\u043a\u0442\u0443\u0440\u0443)", "salary_min": null, "salary_max": null, "salary_currency": null, "vacancy_link": "https://novosibirsk.hh.ru/vacancy/44652464", "site": "hh.ru"}, {"vacancy_name": "\u0420\u0430\u0437\u0440\u0430\u0431\u043e\u0442\u0447\u0438\u043a Python, \u041f\u043e\u0438\u0441\u043a / \u0421\u0442\u0435\u043d\u0434 \u043c\u0435\u0442\u0440\u0438\u043a", "salary_min": null, "salary_max": null, "salary_currency": null, "vacancy_link": "https://novosibirsk.hh.ru/vacancy/43465258", "site": "hh.ru"}, {"vacancy_name": "Python Engineering Manager", "salary_min": null, "salary_max": null, "salary_currency": null, "vacancy_link": "https://novosibirsk.hh.ru/vacancy/45655161", "site": "hh.ru"}, {"vacancy_name": "Fullstack-\u0440\u0430\u0437\u0440\u0430\u0431\u043e\u0442\u0447\u0438\u043a (Python, React)", "salary_min": null, "salary_max": null, "salary_currency": null, "vacancy_link": "https://novosibirsk.hh.ru/vacancy/45655376", "site": "hh.ru"}, {"vacancy_name": "\u0412\u0435\u0431-\u0440\u0430\u0437\u0440\u0430\u0431\u043e\u0442\u0447\u0438\u043a Full stack (Java,JS, Python, XS, HTML5)", "salary_min": null, "salary_max": null, "salary_currency": null, "vacancy_link": "https://novosibirsk.hh.ru/vacancy/45662454", "site": "hh.ru"}, {"vacancy_name": "\u041f\u0440\u0435\u043f\u043e\u0434\u0430\u0432\u0430\u0442\u0435\u043b\u044c \u043f\u043e Python \u0438/\u0438\u043b\u0438 Scratch \u0432 \u043e\u043d\u043b\u0430\u0439\u043d-\u0448\u043a\u043e\u043b\u0443 \u043f\u043e \u043f\u0440\u043e\u0433\u0440\u0430\u043c\u043c\u0438\u0440\u043e\u0432\u0430\u043d\u0438\u044e (\u0443\u0434\u0430\u043b\u0451\u043d\u043d\u043e)", "salary_min": null, "salary_max": null, "salary_currency": null, "vacancy_link": "https://novosibirsk.hh.ru/vacancy/45646812", "site": "hh.ru"}, {"vacancy_name": "QA engineer (Python)", "salary_min": null, "salary_max": null, "salary_currency": null, "vacancy_link": "https://novosibirsk.hh.ru/vacancy/44879853", "site": "hh.ru"}, {"vacancy_name": "Python Engineering Manager", "salary_min": null, "salary_max": null, "salary_currency": null, "vacancy_link": "https://novosibirsk.hh.ru/vacancy/45655162", "site": "hh.ru"}, {"vacancy_name": "\u041f\u0440\u0435\u043f\u043e\u0434\u0430\u0432\u0430\u0442\u0435\u043b\u044c \u043f\u043e Python \u0434\u043b\u044f \u0448\u043a\u043e\u043b\u044c\u043d\u0438\u043a\u043e\u0432 \u0432 TutGood", "salary_min": null, "salary_max": null, "salary_currency": null, "vacancy_link": "https://novosibirsk.hh.ru/vacancy/45681676", "site": "hh.ru"}, {"vacancy_name": "Python \u0440\u0430\u0437\u0440\u0430\u0431\u043e\u0442\u0447\u0438\u043a (fullstack, \u043f\u0440\u043e\u0434\u0443\u043a\u0442\u043e\u0432\u0430\u044f \u0440\u0430\u0437\u0440\u0430\u0431\u043e\u0442\u043a\u0430)", "salary_min": null, "salary_max": null, "salary_currency": null, "vacancy_link": "https://novosibirsk.hh.ru/vacancy/45628591", "site": "hh.ru"}, {"vacancy_name": "\u041f\u0440\u0435\u043f\u043e\u0434\u0430\u0432\u0430\u0442\u0435\u043b\u044c \u043f\u043e \u044f\u0437\u044b\u043a\u0443 Python", "salary_min": null, "salary_max": null, "salary_currency": null, "vacancy_link": "https://novosibirsk.hh.ru/vacancy/41554509", "site": "hh.ru"}, {"vacancy_name": "\u0418\u043d\u0436\u0435\u043d\u0435\u0440 \u043f\u043e \u0430\u0432\u0442\u043e\u043c\u0430\u0442\u0438\u0437\u0430\u0446\u0438\u0438 \u0442\u0435\u0441\u0442\u0438\u0440\u043e\u0432\u0430\u043d\u0438\u044f Python, \u041b\u043e\u0433\u0438\u0441\u0442\u0438\u043a\u0430/\u0422\u0430\u0440\u0438\u0444\u0438\u043a\u0430\u0442\u043e\u0440", "salary_min": null, "salary_max": null, "salary_currency": null, "vacancy_link": "https://novosibirsk.hh.ru/vacancy/35704998", "site": "hh.ru"}, {"vacancy_name": "\u0418\u043d\u0436\u0435\u043d\u0435\u0440 \u043f\u043e \u0430\u0432\u0442\u043e\u043c\u0430\u0442\u0438\u0437\u0438\u0440\u043e\u0432\u0430\u043d\u043d\u043e\u043c\u0443 \u0442\u0435\u0441\u0442\u0438\u0440\u043e\u0432\u0430\u043d\u0438\u044e (QA Automation Engineer) Python, C", "salary_min": null, "salary_max": null, "salary_currency": null, "vacancy_link": "https://novosibirsk.hh.ru/vacancy/45628289", "site": "hh.ru"}, {"vacancy_name": "DevOps-\u0438\u043d\u0436\u0435\u043d\u0435\u0440 (bash/python)", "salary_min": null, "salary_max": null, "salary_currency": null, "vacancy_link": "https://novosibirsk.hh.ru/vacancy/44527690", "site": "hh.ru"}, {"vacancy_name": "\u0412\u0435\u0434\u0443\u0449\u0438\u0439 \u0430\u043d\u0430\u043b\u0438\u0442\u0438\u043a (SQL, PL/SQL, Python)", "salary_min": null, "salary_max": null, "salary_currency": null, "vacancy_link": "https://novosibirsk.hh.ru/vacancy/45654475", "site": "hh.ru"}, {"vacancy_name": "\u0418\u043d\u0436\u0435\u043d\u0435\u0440 \u043f\u043e \u0430\u0432\u0442\u043e\u043c\u0430\u0442\u0438\u0437\u0430\u0446\u0438\u0438 \u0442\u0435\u0441\u0442\u0438\u0440\u043e\u0432\u0430\u043d\u0438\u044f Python, \u041b\u043e\u0433\u0438\u0441\u0442\u0438\u043a\u0430/\u041f\u0440\u0435\u0442\u0435\u043d\u0437\u0438\u043e\u043d\u043d\u0430\u044f \u0440\u0430\u0431\u043e\u0442\u0430", "salary_min": null, "salary_max": null, "salary_currency": null, "vacancy_link": "https://novosibirsk.hh.ru/vacancy/45650645", "site": "hh.ru"}, {"vacancy_name": "\u0418\u043d\u0436\u0435\u043d\u0435\u0440 \u043f\u043e \u0430\u0432\u0442\u043e\u043c\u0430\u0442\u0438\u0437\u0430\u0446\u0438\u0438 \u0442\u0435\u0441\u0442\u0438\u0440\u043e\u0432\u0430\u043d\u0438\u044f Python, \u041b\u043e\u0433\u0438\u0441\u0442\u0438\u043a\u0430/\u041f\u0440\u0435\u0442\u0435\u043d\u0437\u0438\u043e\u043d\u043d\u0430\u044f \u0440\u0430\u0431\u043e\u0442\u0430", "salary_min": null, "salary_max": null, "salary_currency": null, "vacancy_link": "https://novosibirsk.hh.ru/vacancy/45650644", "site": "hh.ru"}, {"vacancy_name": "\u0421\u043f\u0435\u0446\u0438\u0430\u043b\u0438\u0441\u0442 \u043f\u043e \u0430\u0432\u0442\u043e\u043c\u0430\u0442\u0438\u0437\u0430\u0446\u0438\u0438 \u0442\u0435\u0441\u0442\u0438\u0440\u043e\u0432\u0430\u043d\u0438\u044f (Python)", "salary_min": null, "salary_max": null, "salary_currency": null, "vacancy_link": "https://novosibirsk.hh.ru/vacancy/45607865", "site": "hh.ru"}, {"vacancy_name": "\u0418\u043d\u0436\u0435\u043d\u0435\u0440 \u043f\u043e \u0430\u0432\u0442\u043e\u043c\u0430\u0442\u0438\u0437\u0430\u0446\u0438\u0438 \u0442\u0435\u0441\u0442\u0438\u0440\u043e\u0432\u0430\u043d\u0438\u044f Python, \u041b\u043e\u0433\u0438\u0441\u0442\u0438\u043a\u0430/\u0426\u0435\u043d\u0442\u0440\u0430\u043b\u044c\u043d\u044b\u0435 \u043b\u043e\u0433\u0438\u0441\u0442\u0438\u0447\u0435\u0441\u043a\u0438\u0435 \u0441\u0438\u0441\u0442\u0435\u043c\u044b", "salary_min": null, "salary_max": null, "salary_currency": null, "vacancy_link": "https://novosibirsk.hh.ru/vacancy/32695277", "site": "hh.ru"}, {"vacancy_name": "QA Automation Engineer (Python \\ PowerShell)", "salary_min": null, "salary_max": null, "salary_currency": null, "vacancy_link": "https://novosibirsk.hh.ru/vacancy/42715994", "site": "hh.ru"}, {"vacancy_name": "\u0421\u043f\u0435\u0446\u0438\u0430\u043b\u0438\u0441\u0442 \u043f\u043e \u0430\u0432\u0442\u043e\u043c\u0430\u0442\u0438\u0437\u0430\u0446\u0438\u0438 \u0442\u0435\u0441\u0442\u0438\u0440\u043e\u0432\u0430\u043d\u0438\u044f (Python)", "salary_min": null, "salary_max": null, "salary_currency": null, "vacancy_link": "https://novosibirsk.hh.ru/vacancy/44073504", "site": "hh.ru"}, {"vacancy_name": "\u0410\u043d\u0430\u043b\u0438\u0442\u0438\u043a \u0434\u0430\u043d\u043d\u044b\u0445 (SQL,EXCEL,Python),", "salary_min": null, "salary_max": null, "salary_currency": null, "vacancy_link": "https://novosibirsk.hh.ru/vacancy/45619466", "site": "hh.ru"}, {"vacancy_name": "Senior Python Engineer", "salary_min": null, "salary_max": null, "salary_currency": null, "vacancy_link": "https://novosibirsk.hh.ru/vacancy/41678083", "site": "hh.ru"}, {"vacancy_name": "Cloud Python Engineer", "salary_min": null, "salary_max": null, "salary_currency": null, "vacancy_link": "https://novosibirsk.hh.ru/vacancy/43680145", "site": "hh.ru"}, {"vacancy_name": "\u0410\u043d\u0430\u043b\u0438\u0442\u0438\u043a (Python/SQL)", "salary_min": null, "salary_max": null, "salary_currency": null, "vacancy_link": "https://novosibirsk.hh.ru/vacancy/45265255", "site": "hh.ru"}, {"vacancy_name": "Fullstack \u0440\u0430\u0437\u0440\u0430\u0431\u043e\u0442\u0447\u0438\u043a (python/javascript) middle+", "salary_min": null, "salary_max": null, "salary_currency": null, "vacancy_link": "https://novosibirsk.hh.ru/vacancy/45293441", "site": "hh.ru"}, {"vacancy_name": "\u0421\u043f\u0435\u0446\u0438\u0430\u043b\u0438\u0441\u0442 \u043f\u043e \u0430\u0432\u0442\u043e\u043c\u0430\u0442\u0438\u0437\u0438\u0440\u043e\u0432\u0430\u043d\u043d\u043e\u043c\u0443 \u0442\u0435\u0441\u0442\u0438\u0440\u043e\u0432\u0430\u043d\u0438\u044e/Python QA automation engineer", "salary_min": null, "salary_max": null, "salary_currency": null, "vacancy_link": "https://novosibirsk.hh.ru/vacancy/42937498", "site": "hh.ru"}, {"vacancy_name": "\u0418\u043d\u0436\u0435\u043d\u0435\u0440 \u043f\u043e \u0430\u0432\u0442\u043e\u043c\u0430\u0442\u0438\u0437\u0430\u0446\u0438\u0438 \u0442\u0435\u0441\u0442\u0438\u0440\u043e\u0432\u0430\u043d\u0438\u044f (Python)", "salary_min": null, "salary_max": null, "salary_currency": null, "vacancy_link": "https://novosibirsk.hh.ru/vacancy/45272857", "site": "hh.ru"}, {"vacancy_name": "\u0421\u043f\u0435\u0446\u0438\u0430\u043b\u0438\u0441\u0442 \u043f\u043e \u0430\u0432\u0442\u043e\u043c\u0430\u0442\u0438\u0437\u0438\u0440\u043e\u0432\u0430\u043d\u043d\u043e\u043c\u0443 \u0442\u0435\u0441\u0442\u0438\u0440\u043e\u0432\u0430\u043d\u0438\u044e/Python QA automation engineer", "salary_min": null, "salary_max": null, "salary_currency": null, "vacancy_link": "https://novosibirsk.hh.ru/vacancy/42937500", "site": "hh.ru"}, {"vacancy_name": "\u0418\u043d\u0436\u0435\u043d\u0435\u0440 \u043f\u043e \u0430\u0432\u0442\u043e\u043c\u0430\u0442\u0438\u0437\u0430\u0446\u0438\u0438 \u0442\u0435\u0441\u0442\u0438\u0440\u043e\u0432\u0430\u043d\u0438\u044f Python, \u041b\u043e\u0433\u0438\u0441\u0442\u0438\u043a\u0430 / TMS", "salary_min": null, "salary_max": null, "salary_currency": null, "vacancy_link": "https://novosibirsk.hh.ru/vacancy/42878583", "site": "hh.ru"}, {"vacancy_name": "\u0421\u043f\u0435\u0446\u0438\u0430\u043b\u0438\u0441\u0442 \u043f\u043e \u0430\u0432\u0442\u043e\u043c\u0430\u0442\u0438\u0437\u0438\u0440\u043e\u0432\u0430\u043d\u043d\u043e\u043c\u0443 \u0442\u0435\u0441\u0442\u0438\u0440\u043e\u0432\u0430\u043d\u0438\u044e/Python QA automation engineer", "salary_min": null, "salary_max": null, "salary_currency": null, "vacancy_link": "https://novosibirsk.hh.ru/vacancy/42336120", "site": "hh.ru"}, {"vacancy_name": "\u0421\u043f\u0435\u0446\u0438\u0430\u043b\u0438\u0441\u0442 \u043f\u043e \u0430\u0432\u0442\u043e\u043c\u0430\u0442\u0438\u0437\u0438\u0440\u043e\u0432\u0430\u043d\u043d\u043e\u043c\u0443 \u0442\u0435\u0441\u0442\u0438\u0440\u043e\u0432\u0430\u043d\u0438\u044e/Python QA automation engineer", "salary_min": null, "salary_max": null, "salary_currency": null, "vacancy_link": "https://novosibirsk.hh.ru/vacancy/42937499", "site": "hh.ru"}, {"vacancy_name": "Fullstack \u0440\u0430\u0437\u0440\u0430\u0431\u043e\u0442\u0447\u0438\u043a (python/javascript)", "salary_min": null, "salary_max": null, "salary_currency": null, "vacancy_link": "https://novosibirsk.hh.ru/vacancy/45250784", "site": "hh.ru"}, {"vacancy_name": "Python \u0440\u0430\u0437\u0440\u0430\u0431\u043e\u0442\u0447\u0438\u043a (\u0412\u0438\u0440\u0442\u0443\u0430\u043b\u044c\u043d\u044b\u0439 \u043f\u0435\u0440\u0441\u043e\u043d\u0430\u043b\u044c\u043d\u044b\u0439 \u0444\u0438\u043d\u0430\u043d\u0441\u043e\u0432\u044b\u0439 \u0430\u0441\u0441\u0438\u0441\u0442\u0435\u043d\u0442)", "salary_min": null, "salary_max": null, "salary_currency": null, "vacancy_link": "https://novosibirsk.hh.ru/vacancy/44984138", "site": "hh.ru"}, {"vacancy_name": "Backend-\u0440\u0430\u0437\u0440\u0430\u0431\u043e\u0442\u0447\u0438\u043a (PHP/Python/Golang)", "salary_min": null, "salary_max": null, "salary_currency": null, "vacancy_link": "https://novosibirsk.hh.ru/vacancy/45407369", "site": "hh.ru"}, {"vacancy_name": "Software Engineer (Python) (Cyprus, Limassol / Remotely)", "salary_min": null, "salary_max": null, "salary_currency": null, "vacancy_link": "https://novosibirsk.hh.ru/vacancy/45383895", "site": "hh.ru"}, {"vacancy_name": "Middle Backend Python developer (Node.JS or PHP)", "salary_min": null, "salary_max": null, "salary_currency": null, "vacancy_link": "https://novosibirsk.hh.ru/vacancy/45337937", "site": "hh.ru"}, {"vacancy_name": "Python Full-stack web developer Senior/Middle (remote)", "salary_min": null, "salary_max": null, "salary_currency": null, "vacancy_link": "https://novosibirsk.hh.ru/vacancy/45457836", "site": "hh.ru"}, {"vacancy_name": "Full stack programmer (Python/JavaSript/HTML/CSS), \u0443\u0434\u0430\u043b\u0451\u043d\u043d\u043e", "salary_min": null, "salary_max": null, "salary_currency": null, "vacancy_link": "https://novosibirsk.hh.ru/vacancy/45238208", "site": "hh.ru"}, {"vacancy_name": "\u041f\u0440\u043e\u0433\u0440\u0430\u043c\u043c\u0438\u0441\u0442 1\u0421 / Python", "salary_min": null, "salary_max": null, "salary_currency": null, "vacancy_link": "https://novosibirsk.hh.ru/vacancy/44810466", "site": "hh.ru"}, {"vacancy_name": "Python Developer (Payment Systems Team, remotely)", "salary_min": null, "salary_max": null, "salary_currency": null, "vacancy_link": "https://novosibirsk.hh.ru/vacancy/45383743", "site": "hh.ru"}, {"vacancy_name": "\u0420\u0443\u0441\u0441\u043a\u043e\u044f\u0437\u044b\u0447\u043d\u044b\u0439 \u043f\u0440\u0435\u043f\u043e\u0434\u0430\u0432\u0430\u0442\u0435\u043b\u044c Python", "salary_min": null, "salary_max": null, "salary_currency": null, "vacancy_link": "https://novosibirsk.hh.ru/vacancy/45880845", "site": "hh.ru"}]